Workbook

Sheet DATOS
B3: EJERCICIO INTEGRAL DE COSTOS POR ÓRDENES DE PRODUCCION
B5: La empresa industria de producción textil de camisetas “ALAN SPORT” fabrica camisetas polo para hombre de las tallas S,M,L. Trabaja bajo un sistema de costos por órdenes de producción.
B8: PRODUCTO | C8: TELA | D8: CUELLO | E8: PUÑOS | F8: BOTON | G8: HILO
B9: Camiseta S | C9: 80 cm | D9: 1 | E9: 2 | F9: 2 | G9: 4mt
B10: Camiseta M | C10: 90 cm | D10: 1 | E10: 2 | F10: 2 | G10: 5mt
B11: Camiseta L | C11: 1,10 cm | D11: 1 | E11: 2 | F11: 2 | G11: 6mt | H11: 15 | I11: DIARIO | J11: 3 DIAS
B12: PRECIO U. | C12: 4.2 | D12: 0.5 | E12: 0.2 | F12: 0.05 | G12: 3 | H12: =C24*H11 -> 150000 | I12: =H12/5 -> 30000 | J12: =I12*3 -> 90000
B14: Sus datos iniciales de inventario son
B15: PRODUCTO | C15: TELA | D15: CUELLO | E15: PUÑOS | F15: BOTON | G15: HILO
C16: 100 rollos 45mt | D16: 3000 | E16: 5000 | F16: 40000 | G16: 100 Conos
B19: En una semana de producción se produce
B20: PRODUCTO | C20: CANTIDAD
B21: Camiseta S | C21: 3000 | D21: =C21*80 -> 240000
B22: Camiseta M | C22: 3700 | D22: =C22*90 -> 333000
B23: Camiseta L | C23: 3300 | D23: =C23*110 -> 363000
C24: 10000 | D24: =SUM(D21:D23) -> 936000 | F24: STOCK
C25: METROS: | D25: =D24/100 -> 9360 | E25: =D25/5 -> 1872 | F25: =E25*3 -> 5616
B28: Además, tiene en el banco $ 80.000, en maquinaria $70.000,00, debe a proveedores $15000 y en sus ventas se margina una utilidad del 80%, la empresa cuenta con los siguientes trabajadores:
B29: 30 obreros con un sueldo básico de $482, el 50% de ellos trabajan más de un año, horas extras frecuentes de 4 normales y 8 extraordinarias, se considera que el 25% del tiempo se destina a fabricar la talla S, el 40% la M y el 35% la L.
B32: 1 jefe de producción y 1 supervisor con un sueldo de $ 700 y $ 650 respectivamente, todos trabajan más de un año, bonos de producción frecuentes de $ 60 y $ 100 respectivamente. Sus pagos son semanalmente.
B35: En lo referente a los costos indirectos de fabricación la empresa determina su aplicación en base a unidades producidas y que como costos indirectos mensuales tenemos energía eléctrica $500, mantenimiento $25 por máquina, seguros de fabrica $350 y la correspondiente depreciación.
B39: Las órdenes de producción durante el mes de enero del 2026 fueron las siguientes:
B41: Enero 05: se recibe un pedido por parte TOMY para una producción de
B43: PRODUCTO | C43: CANTIDAD
B44: Camiseta S | C44: 4000
B45: Camiseta M | C45: 6000
B46: Camiseta L | C46: 5000 | D46: =C44+C45+C46 -> 15000
B48: La fecha estimada de entrega es el
B49: ENERO : se recibe un pedido de TEXPAX para la fabricación de
B51: PRODUCTO | C51: CANTIDAD
B52: Camiseta S | C52: 5000
B53: Camiseta M | C53: 6000
B54: Camiseta L | C54: 9000
D55: =C52+C53+C54 -> 20000
B56: La fecha estimada de entrega es el
B57: Para la fabricación y venta se asume que la empresa compra lo necesario para su producción con un incremento del 10%, y vende sus productos en las fechas terminadas con el 80% de ganancia.
B60: Comprar materia prima y mandar a produccion, 2, 3

Sheet LIBRO DIARIO
B2: INDUSTRIAS "ALAN SPORT"
B3: LIBRO DIARIO
F5: FOLIO: | G5: 1
B6: FECHA | C6: DETALLE | D6: N/M | E6: PARCIAL | F6: DEBE | G6: HABER
B7: 46027 | C7: --------------------------- 1 ---------------------------
C8: BANCOS | D8: 1 | F8: 80000
C9: INV. MATERIA PRIMA DIRECTA | D9: 2 | F9: =KARDEX!L9+KARDEX!L25+KARDEX!L41+KARDEX!L57 -> 23400
C10: INV. MATERIA PRIMA INDIRECTA | D10: 3 | F10: =KARDEX!L73 -> 300
C11: MAQUINARIA | D11: 4 | F11: 70000
C12: PROVEEDORES | D12: 5 | G12: 15000
C13: CAPITAL | D13: 6 | G13: =(F8+F9+F10+F11)-G12 -> 158700
C14: P/R la situació inicial de la industria
B15: 46027 | C15: --------------------------- 2 ---------------------------
C16: INV. MATERIA PRIMA DIRECTA | D16: 2 | F16: =KARDEX!F10+KARDEX!F26+KARDEX!F42+KARDEX!F58 -> 88447.92
C17: INV. MATERIA PRIMA DIRECTA | D17: 3 | F17: =KARDEX!F75 -> 0
C18: PROVEEDORES | D18: 5 | G18: =F16+F17 -> 88447.92
C19: P/R la compra de materia prima para la OP#100 a crédito
B20: 46027 | C20: --------------------------- 3 ---------------------------
C21: PRODUCCIÓN PROCESO OP#100 TS | D21: 7 | F21: =KARDEX!I11+KARDEX!I27+KARDEX!I43+KARDEX!I59+KARDEX!I75 -> 18807.53
C22: PRODUCCIÓN PROCESO OP#100 TM | D22: 8 | F22: =KARDEX!I12+KARDEX!I28+KARDEX!I44+KARDEX!I60+KARDEX!I76 -> 30931.778
C23: PRODUCCIÓN PROCESO OP#100 TL | D23: 9 | F23: =KARDEX!I13+KARDEX!I29+KARDEX!I45+KARDEX!I61+KARDEX!I77 -> 30305.62
C24: INV. MATERIA PRIMA DIRECTA | D24: 2 | G24: =KARDEX!I11+KARDEX!I12+KARDEX!I13+KARDEX!I27+KARDEX!I28+KARDEX!I30+KARDEX!I43+KARDEX!I44+KARDEX!I45+KARDEX!I59+KARDEX!I60+KARDEX!I61 -> 77254.642
C25: INV. MATERIA PRIMA INDIRECTA | D25: 3 | G25: =KARDEX!I75+KARDEX!I76+KARDEX!I77 -> 76
C26: P/R el envio de materia prima directa e indirecta para la OP#100
B27: 46031 | C27: --------------------------- 4 ---------------------------
C28: MANO DE OBRA DIRECTA | D28: 10 | F28: =('ROL MOD'!G35+'ROL MOD'!H35+'ROL MOD'!I35+'ROL MOD'!J35+'ROL MOD'!K35+'ROL MOD'!L35+'ROL MOD'!F77+'ROL MOD'!G77+'ROL MOD'!H77+'ROL MOD'!I77+'ROL MOD'!J77)/4 -> 5598.2718
C29: MANO DE OBRA INDIRECTA | D29: 11 | F29: =('ROL MOD'!G41+'ROL MOD'!H41+'ROL MOD'!I41+'ROL MOD'!J41+'ROL MOD'!K41+'ROL MOD'!L41+'ROL MOD'!F83+'ROL MOD'!G83+'ROL MOD'!H83+'ROL MOD'!I83+'ROL MOD'!J83)/4 -> 583.80799
C30: IESS POR PAGAR | D30: 12 | G30: =('ROL MOD'!N35+'ROL MOD'!N41+'ROL MOD'!J77+'ROL MOD'!J83)/4 -> 979.76925
C31: XIII SUELDO POR PAGAR | D31: 13 | G31: =('ROL MOD'!F77+'ROL MOD'!F83)/4 -> 377.9974
C32: XIV SUELDO POR PAGAR | D32: 14 | G32: =('ROL MOD'!G77+'ROL MOD'!G83)/4 -> 321.33333
C33: VACACIONES | D33: 15 | G33: =('ROL MOD'!H77+'ROL MOD'!H83)/4 -> 188.9987
C34: BANCOS | D34: 1 | G34: =('ROL MOD'!S35+'ROL MOD'!S41)/4 -> 4313.9812
C35: P/R el pago de la mod y moi de una semana de la op#100
B36: =B27 -> 46031 | C36: --------------------------- 5 ---------------------------
C37: PRODUCCIÓN PROCESO OP#100 TS | D37: 7 | F37: =(G40*25%)+(G41*25%) -> 1545.52
C38: PRODUCCIÓN PROCESO OP#100 TM | D38: 8 | F38: =(G40*40%)+(G41*40%) -> 2472.8319
C39: PRODUCCIÓN PROCESO OP#100 TL | D39: 9 | F39: =(G40*35%)+(G41*35%) -> 2163.7279
C40: MANO DE OBRA DIRECTA | G40: =F28 -> 5598.2718
C41: MANO DE OBRA INDIRECTA | G41: =F29 -> 583.80799
C42: P/R el cargo de la mod y moi para OP#100
B43: 46036 | C43: --------------------------- 6 ---------------------------
C44: MANO DE OBRA DIRECTA | D44: 10 | F44: =(F28/5)*3 -> 3358.9631
C45: MANO DE OBRA INDIRECTA | D45: 11 | F45: =(F29/5)*3 -> 350.2848
C46: IESS POR PAGAR | D46: 12 | G46: =(G30/5)*3 -> 587.86155
C47: XIII SUELDO POR PAGAR | D47: 13 | G47: =(G31/5)*3 -> 226.79844
C48: XIV SUELDO POR PAGAR | D48: 14 | G48: =(G32/5)*3 -> 192.8
C49: VACACIONES | D49: 15 | G49: =(G33/5)*3 -> 113.39922
C50: SUELDOS POR PAGAR | D50: 16 | G50: =(G34/5)*3 -> 2588.3887
C51: P/R el pago de la mod y moi de tres dias de la op#100
B52: =B43 -> 46036 | C52: --------------------------- 7 ---------------------------
C53: PRODUCCIÓN PROCESO OP#100 TS | D53: 7 | F53: =(G56*25%)+(G57*25%) -> 927.31198
C54: PRODUCCIÓN PROCESO OP#100 TS | D54: 8 | F54: =(G56*40%)+(G57*40%) -> 1483.6992
C55: PRODUCCIÓN PROCESO OP#100 TS | D55: 9 | F55: =(G56*35%)+(G57*35%) -> 1298.2368
C56: MANO DE OBRA DIRECTA | D56: 10 | G56: =F44 -> 3358.9631
C57: MANO DE OBRA INDIRECTA | D57: 11 | G57: =F45 -> 350.2848
C58: P/R el cargo de la mod y moi de 3 dias para OP#100
B59: =B52 -> 46036 | C59: --------------------------- 8 ---------------------------
C60: ENERGÍA ELÉCTRICA | D60: 17 | F60: =CÁLCULOS!J64 -> 187.5
C61: MANTENIMIENTO | D61: 18 | F61: =CÁLCULOS!J65 -> 281.25
C62: SEGUROS DE FÁBRICA | D62: 19 | F62: =CÁLCULOS!J66 -> 131.25
C63: DEPRECIACIÓN MAQUINARIA | D63: 20 | F63: =CÁLCULOS!J67 -> 218.75
C64: CUENTAS POR PAGAR | D64: 21 | G64: =F60+F61+F62 -> 600
C65: DEPRE. ACUM. MAQUINARIA | D65: 22 | G65: =F63 -> 218.75
C66: P/R el presupuesto de producción de cif para la OP#100
B67: =B59 -> 46036 | C67: --------------------------- 9 ---------------------------
C68: COSTOS INDIRECTOS FÁBRICA | D68: 23 | F68: =SUM(G69:G72) -> 818.75
C69: ENERGÍA ELÉCTRICA | D69: 17 | G69: =F60 -> 187.5
C70: MANTENIMIENTO | D70: 18 | G70: =F61 -> 281.25
C71: SEGUROS DE FÁBRICA | D71: 19 | G71: =F62 -> 131.25
C72: DEPRECIACIÓN MAQUINARIA | D72: 20 | G72: =F63 -> 218.75
C73: P/R la determinación de los cif para la OP#100
B74: =B67 -> 46036 | C74: --------------------------- 10 ---------------------------
C75: PRODUCCIÓN PROCESO OP#100 TS | D75: 7 | F75: =CÁLCULOS!G68 -> 218.33333
C76: PRODUCCIÓN PROCESO OP#100 TM | D76: 8 | F76: =CÁLCULOS!H68 -> 327.5
C77: PRODUCCIÓN PROCESO OP#100 TL | D77: 9 | F77: =CÁLCULOS!I68 -> 272.91667
C78: COSTOS INDIRECTOS DE FÁBRICA | D78: 23 | G78: =F68 -> 818.75
C79: P/R el cargo de la mod y moi de 3 días para OP#100
B80: =B74 -> 46036 | C80: --------------------------- 11 ---------------------------
C81: PRODUCTO TERMINADO OP#100 TS | D81: 24 | F81: =G84 -> 21498.695
C82: PRODUCTO TERMINADO OP#100 TM | D82: 25 | F82: =G85 -> 35215.809
C83: PRODUCTO TERMINADO OP#100 TL | D83: 26 | F83: =G86 -> 34040.502
C84: PRODUCCIÓN PROCESO OP#100 TS | D84: 7 | G84: =MAYORIZACIÓN!F54 -> 21498.695
C85: PRODUCCIÓN PROCESO OP#100 TM | D85: 8 | G85: =MAYORIZACIÓN!N54 -> 35215.809
C86: PRODUCCIÓN PROCESO OP#100 TL | D86: 9 | G86: =MAYORIZACIÓN!F68 -> 34040.502
C87: P/R productos terminados entregados por producción de OP#100
B88: =B80 -> 46036 | C88: --------------------------- 12 ---------------------------
C89: CAJA | D89: 27 | F89: =G90 -> 163359.01
C90: VENTAS | D90: 28 | G90: =CÁLCULOS!E75 -> 163359.01
C91: P/R la venta de contado de los productos terminados de OP#100
B92: =B80 -> 46036 | C92: --------------------------- 12.1 ---------------------------
C93: COSTO DE PRODUCCIÓN Y VENTA | F93: =SUM(G94:G96) -> 90755.006
C94: PRODUCTO TERMINADO OP#100 TS | D94: 24 | G94: =KARDEX!I89 -> 21498.695
C95: PRODUCTO TERMINADO OP#100 TM | G95: =KARDEX!I103 -> 35215.809
C96: PRODUCTO TERMINADO OP#100 TL | G96: =KARDEX!I117 -> 34040.502
C97: P/R el costo de los productos terminados y vendidos de OP#100
B98: 46037 | C98: --------------------------- 13 ---------------------------
C99: INV. MATERIA PRIMA DIRECTA | D99: 2 | F99: =KARDEX!F14+KARDEX!F30+KARDEX!F46+KARDEX!F62 -> 122282.6
C100: INV. MATERIA PRIMA DIRECTA | D100: 3 | F100: =KARDEX!F158 -> 0
C101: PROVEEDORES | D101: 5 | G101: =F99+F100 -> 122282.6
C102: P/R la compra de materia prima para la OP#100 a crédito
...

Sheet MAYORIZACIÓN
B3: Industrias "ALAN SPORT" | J3: Industrias "ALAN SPORT"
B4: LIBRO MAYOR | J4: LIBRO MAYOR
B5: CUENTA | C5: ='LIBRO DIARIO'!C8 -> BANCOS | G5: No | H5: 1 | J5: CUENTA | K5: ='LIBRO DIARIO'!C9 -> INV. MATERIA PRIMA DIRECTA | O5: No | P5: 2
B6: FECHA | C6: DETALLE | D6: F | E6: A | F6: DEBE | G6: HABER | H6: SALDO | J6: FECHA | K6: DETALLE | L6: F | M6: A | N6: DEBE | O6: HABER | P6: SALDO
B7: ='LIBRO DIARIO'!B7 -> 46027 | C7: A VARIOS | D7: 1 | E7: 1 | F7: ='LIBRO DIARIO'!F8 -> 80000 | H7: =F7-G7 -> 80000 | J7: ='LIBRO DIARIO'!B7 -> 46027 | K7: A VARIOS | L7: 1 | M7: 1 | N7: ='LIBRO DIARIO'!F9 -> 23400 | P7: =N7-O7 -> 23400
B8: ='LIBRO DIARIO'!B27 -> 46031 | C8: POR MOD Y MOI | D8: 1 | E8: 4 | G8: ='LIBRO DIARIO'!G34 -> 4313.9812 | H8: =(H7+F8)-G8 -> 75686.019 | J8: ='LIBRO DIARIO'!B15 -> 46027 | K8: A PROVEEDORES | L8: 1 | M8: 2 | N8: ='LIBRO DIARIO'!F16 -> 88447.92 | P8: =(P7+N8)-O8 -> 111847.92
B9: ='[1]LIBRO DIARIO'!B26 -> 46030 | C9: A VENTAS | D9: 1 | E9: 5 | F9: ='[1]LIBRO DIARIO'!F27 -> 83661.111 | H9: =(H8+F9)-G9 -> 159347.13 | J9: ='LIBRO DIARIO'!B20 -> 46027 | K9: POR PRODUCCIÓN.PROCESO | L9: 1 | M9: 3 | O9: ='LIBRO DIARIO'!G24 -> 77254.642 | P9: =(P8+N9)-O9 -> 34593.278 | Q9: 79698.93
B10: ='[1]LIBRO DIARIO'!B26 -> 46030 | C10: POR BANCOS | D10: 1 | E10: 7 | G10: ='[1]LIBRO DIARIO'!G36 -> 81987.889 | H10: =(H9+F10)-G10 -> 77359.241 | J10: ='[1]LIBRO DIARIO'!B42 -> 46035 | K10: A PROVEEDORES | L10: 1 | M10: 8 | N10: ='[1]LIBRO DIARIO'!F43 -> 67500 | P10: =(P9+N10)-O10 -> 102093.28
B11: ='[1]LIBRO DIARIO'!B46 -> 46037 | C11: A VENTAS | D11: 1 | E11: 9 | F11: ='[1]LIBRO DIARIO'!F47 -> 44624.035 | H11: =(H10+F11)-G11 -> 121983.28 | J11: ='[1]LIBRO DIARIO'!B46 -> 46037 | K11: POR COSTO DE VENTAS | L11: 1 | M11: 10 | O11: ='[1]LIBRO DIARIO'!G53 -> 69725.054 | P11: =(P10+N11)-O11 -> 32368.223
F13: =SUM(F7:F11) -> 208285.15 | G13: =SUM(G7:G11) -> 86301.87 | H13: =SUM(H7:H11) -> 514375.67 | N13: =SUM(N7:N12) -> 179347.92 | O13: =SUM(O7:O12) -> 146979.7 | P13: =SUM(P7:P12) -> 304302.7
B16: Industrias "ALAN SPORT" | J16: Industrias "ALAN SPORT"
B17: LIBRO MAYOR | J17: LIBRO MAYOR
B18: CUENTA | C18: ='LIBRO DIARIO'!C10 -> INV. MATERIA PRIMA INDIRECTA | G18: No | H18: 3 | J18: CUENTA | K18: ='LIBRO DIARIO'!C11 -> MAQUINARIA | O18: No | P18: 4
B19: FECHA | C19: DETALLE | D19: F | E19: A | F19: DEBE | G19: HABER | H19: SALDO | J19: FECHA | K19: DETALLE | L19: F | M19: A | N19: DEBE | O19: HABER | P19: SALDO
B20: ='LIBRO DIARIO'!B7 -> 46027 | C20: A VARIOS | D20: 1 | E20: 1 | F20: ='LIBRO DIARIO'!F10 -> 300 | H20: =F20-G20 -> 300 | J20: ='LIBRO DIARIO'!B7 -> 46027 | K20: A VARIOS | L20: 1 | M20: 1 | N20: ='LIBRO DIARIO'!F11 -> 70000 | P20: =N20-O20 -> 70000
B21: ='LIBRO DIARIO'!B15 -> 46027 | C21: A PROVEEDORES | D21: 1 | E21: 2 | F21: ='LIBRO DIARIO'!F17 -> 0 | H21: =(H20+F21)-G21 -> 300 | J21: ='[1]LIBRO DIARIO'!B15 -> 46027 | K21: POR MERCADERÍAS | L21: 1 | M21: 3 | O21: ='[1]LIBRO DIARIO'!G17 -> 14850 | P21: =(P20+N21)-O21 -> 55150
B22: ='LIBRO DIARIO'!B20 -> 46027 | C22: POR PRODUCCIÓN. PROCESO | D22: 1 | E22: 3 | G22: ='LIBRO DIARIO'!G25 -> 76 | H22: =(H21+F22)-G22 -> 224 | J22: ='[1]LIBRO DIARIO'!B20 -> 46028 | K22: POR VARIOS | L22: 1 | M22: 3 | O22: ='[1]LIBRO DIARIO'!G24 -> 5800 | P22: =(P21+N22)-O22 -> 49350
J23: ='[1]LIBRO DIARIO'!B26 -> 46030 | K23: A CAJA | L23: 1 | M23: 7 | N23: ='[1]LIBRO DIARIO'!F35 -> 81987.889 | P23: =(P22+N23)-O23 -> 131337.89
J24: ='[1]LIBRO DIARIO'!B38 -> 46034 | K24: POR VEHÍCULOS | L24: 1 | M24: 5 | O24: ='[1]LIBRO DIARIO'!G40 -> 22000 | P24: =(P23+N24)-O24 -> 109337.89
J25: ='[1]LIBRO DIARIO'!B55 -> 46052 | K25: POR GASTO ARRIENDO | L25: 1 | M25: 11 | O25: ='[1]LIBRO DIARIO'!G57 -> 1200 | P25: =(P24+N25)-O25 -> 108137.89
J26: ='[1]LIBRO DIARIO'!B59 -> 46052 | K26: POR GATOS SUELDOS | L26: 1 | M26: 12 | O26: ='[1]LIBRO DIARIO'!G62 -> 5984.046 | P26: =(P25+N26)-O26 -> 102153.84
F27: =SUM(F20:F25) -> 300 | G27: =SUM(G20:G25) -> 76 | H27: =SUM(H20:H25) -> 824 | N27: =SUM(N20:N26) -> 151987.89 | O27: =SUM(O20:O26) -> 49834.046 | P27: =SUM(P20:P26) -> 625467.51
B30: Industrias "ALAN SPORT" | J30: Industrias "ALAN SPORT"
B31: LIBRO MAYOR | J31: LIBRO MAYOR
B32: CUENTA | C32: ='LIBRO DIARIO'!C12 -> PROVEEDORES | G32: No | H32: 5 | J32: CUENTA | K32: ='LIBRO DIARIO'!C13 -> CAPITAL | O32: No | P32: 6
B33: FECHA | C33: DETALLE | D33: F | E33: A | F33: DEBE | G33: HABER | H33: SALDO | J33: FECHA | K33: DETALLE | L33: F | M33: A | N33: DEBE | O33: HABER | P33: SALDO
B34: ='LIBRO DIARIO'!B7 -> 46027 | C34: POR VARIOS | D34: 1 | E34: 1 | F34: ='[1]LIBRO DIARIO'!F33 -> 0 | G34: ='LIBRO DIARIO'!G12 -> 15000 | H34: =G34-F34 -> 15000 | J34: ='LIBRO DIARIO'!B7 -> 46027 | K34: POR VARIOS | L34: 1 | M34: 1 | O34: ='LIBRO DIARIO'!G13 -> 158700 | P34: =O34-N34 -> 158700
B35: ='LIBRO DIARIO'!B15 -> 46027 | C35: POR VARIOS | D35: 1 | E35: 2 | G35: ='LIBRO DIARIO'!G18 -> 88447.92 | H35: =H34+G35-F35 -> 103447.92
F40: =SUM(F34:F39) -> 0 | G40: =SUM(G34:G39) -> 103447.92 | H40: =SUM(H34:H39) -> 118447.92 | N40: =SUM(N34:N39) -> 0 | O40: =SUM(O34:O39) -> 158700 | P40: =SUM(P34:P39) -> 158700
B43: Industrias "ALAN SPORT" | J43: Industrias "ALAN SPORT"
B44: LIBRO MAYOR | J44: LIBRO MAYOR
B45: CUENTA | C45: ='LIBRO DIARIO'!C21 -> PRODUCCIÓN PROCESO OP#100 TS | G45: No | H45: 7 | J45: CUENTA | K45: ='LIBRO DIARIO'!C38 -> PRODUCCIÓN PROCESO OP#100 TM | O45: No | P45: 8
B46: FECHA | C46: DETALLE | D46: F | E46: A | F46: DEBE | G46: HABER | H46: SALDO | J46: FECHA | K46: DETALLE | L46: F | M46: A | N46: DEBE | O46: HABER | P46: SALDO
B47: ='LIBRO DIARIO'!B20 -> 46027 | C47: A VARIOS | D47: 1 | E47: 3 | F47: ='LIBRO DIARIO'!F21 -> 18807.53 | G47: ='[1]LIBRO DIARIO'!G30 -> 0 | H47: =F47-G47 -> 18807.53 | J47: ='LIBRO DIARIO'!B20 -> 46027 | K47: A VARIOS | L47: 1 | M47: 3 | N47: ='LIBRO DIARIO'!F22 -> 30931.778 | O47: ='[1]LIBRO DIARIO'!O30 -> 0 | P47: =N47-O47 -> 30931.778
B48: ='LIBRO DIARIO'!B36 -> 46031 | C48: A MOD Y MOI | D48: 1 | E48: 5 | F48: ='LIBRO DIARIO'!F37 -> 1545.52 | H48: =(H47+F48)-G48 -> 20353.05 | J48: ='LIBRO DIARIO'!B36 -> 46031 | K48: A MOD Y MOI | L48: 1 | M48: 5 | N48: ='LIBRO DIARIO'!F38 -> 2472.8319 | P48: =(P47+N48)-O48 -> 33404.61
B49: ='LIBRO DIARIO'!B52 -> 46036 | C49: A MOD Y MOI | D49: 1 | E49: 7 | F49: ='LIBRO DIARIO'!F53 -> 927.31198 | H49: =(H48+F49)-G49 -> 21280.362 | J49: ='LIBRO DIARIO'!B52 -> 46036 | K49: A MOD Y MOI | L49: 1 | M49: 7 | N49: ='LIBRO DIARIO'!F54 -> 1483.6992 | P49: =(P48+N49)-O49 -> 34888.309
B50: ='LIBRO DIARIO'!B74 -> 46036 | C50: A CIF | D50: 1 | E50: 10 | F50: ='LIBRO DIARIO'!F75 -> 218.33333 | H50: =(H49+F50)-G50 -> 21498.695 | J50: ='LIBRO DIARIO'!B74 -> 46036 | K50: A CIF | L50: 1 | M50: 10 | N50: ='LIBRO DIARIO'!F76 -> 327.5 | P50: =(P49+N50)-O50 -> 35215.809
B51: ='LIBRO DIARIO'!B80 -> 46036 | C51: POR PRO. TERMINADOS TS | D51: 1 | E51: 11 | G51: ='LIBRO DIARIO'!G84 -> 21498.695 | H51: =(H50+F51)-G51 -> 0 | J51: ='LIBRO DIARIO'!B80 -> 46036 | K51: POR PRO. TERMINADOS TM | L51: 1 | M51: 11 | O51: ='LIBRO DIARIO'!G85 -> 35215.809 | P51: =(P50+N51)-O51 -> 0
H52: =(H51+F52)-G52 -> 0
H53: =(H52+F53)-G53 -> 0
F54: =SUM(F47:F53) -> 21498.695 | G54: =SUM(G47:G53) -> 21498.695 | H54: =SUM(H47:H53) -> 81939.636 | N54: =SUM(N47:N53) -> 35215.809 | O54: =SUM(O47:O53) -> 35215.809 | P54: =SUM(P47:P53) -> 134440.51
B57: Industrias "ALAN SPORT" | J57: Industrias "ALAN SPORT"
B58: LIBRO MAYOR | J58: LIBRO MAYOR
B59: CUENTA | C59: ='LIBRO DIARIO'!C39 -> PRODUCCIÓN PROCESO OP#100 TL | G59: No | H59: 9 | J59: CUENTA | K59: ='LIBRO DIARIO'!C28 -> MANO DE OBRA DIRECTA | O59: No | P59: 10
B60: FECHA | C60: DETALLE | D60: F | E60: A | F60: DEBE | G60: HABER | H60: SALDO | J60: FECHA | K60: DETALLE | L60: F | M60: A | N60: DEBE | O60: HABER | P60: SALDO
B61: ='LIBRO DIARIO'!B20 -> 46027 | C61: A VARIOS | D61: 1 | E61: 3 | F61: ='LIBRO DIARIO'!F23 -> 30305.62 | G61: 0 | H61: =F61-G61 -> 30305.62 | J61: ='LIBRO DIARIO'!B27 -> 46031 | K61: A VARIOS | L61: 1 | M61: 4 | N61: ='LIBRO DIARIO'!F28 -> 5598.2718 | O61: ='[1]LIBRO DIARIO'!O28 -> 0 | P61: =N61-O61 -> 5598.2718
B62: ='LIBRO DIARIO'!B36 -> 46031 | C62: A MOD Y MOI | D62: 1 | E62: 5 | F62: ='LIBRO DIARIO'!F39 -> 2163.7279 | H62: =H61+F62-G62 -> 32469.348 | J62: ='LIBRO DIARIO'!B36 -> 46031 | K62: POR PRODUCCIÓN. PROCESO | L62: 1 | M62: 5 | O62: ='LIBRO DIARIO'!G40 -> 5598.2718 | P62: =P61+N62-O62 -> 0
B63: ='LIBRO DIARIO'!B52 -> 46036 | C63: A MOD Y MOI | D63: 1 | E63: 7 | F63: ='LIBRO DIARIO'!F55 -> 1298.2368 | H63: =(H62+F63)-G63 -> 33767.585 | J63: ='LIBRO DIARIO'!B43 -> 46036 | K63: A VARIOS | L63: 1 | M63: 6 | N63: ='LIBRO DIARIO'!F44 -> 3358.9631 | P63: =P62+N63-O63 -> 3358.9631
B64: ='LIBRO DIARIO'!B74 -> 46036 | C64: A CIF | D64: 1 | E64: 10 | F64: ='LIBRO DIARIO'!F77 -> 272.91667 | H64: =(H63+F64)-G64 -> 34040.502 | J64: ='LIBRO DIARIO'!B52 -> 46036 | K64: POR PRODUCCIÓN. PROCESO | L64: 1 | M64: 7 | O64: ='LIBRO DIARIO'!G56 -> 3358.9631 | P64: =P63+N64-O64 -> 0
B65: ='LIBRO DIARIO'!B80 -> 46036 | C65: POR PRO. TERMINADOS TL | D65: 1 | E65: 11 | G65: ='LIBRO DIARIO'!G86 -> 34040.502 | H65: =(H64+F65)-G65 -> 0
F68: =SUM(F61:F67) -> 34040.502 | G68: =SUM(G61:G67) -> 34040.502 | H68: =SUM(H61:H67) -> 130583.06 | N68: =SUM(N61:N67) -> 8957.235 | O68: =SUM(O61:O67) -> 8957.235 | P68: =SUM(P61:P67) -> 8957.235
B71: Industrias "ALAN SPORT" | J71: Industrias "ALAN SPORT"
B72: LIBRO MAYOR | J72: LIBRO MAYOR
B73: CUENTA | C73: ='LIBRO DIARIO'!C29 -> MANO DE OBRA INDIRECTA | G73: No | H73: 11 | J73: CUENTA | K73: ='LIBRO DIARIO'!C30 -> IESS POR PAGAR | O73: No | P73: 12
B74: FECHA | C74: DETALLE | D74: F | E74: A | F74: DEBE | G74: HABER | H74: SALDO | J74: FECHA | K74: DETALLE | L74: F | M74: A | N74: DEBE | O74: HABER | P74: SALDO
B75: ='LIBRO DIARIO'!B27 -> 46031 | C75: A VARIOS | D75: 1 | E75: 4 | F75: ='LIBRO DIARIO'!F29 -> 583.80799 | G75: ='[1]LIBRO DIARIO'!G41 -> 0 | H75: =F75-G75 -> 583.80799 | J75: ='LIBRO DIARIO'!B27 -> 46031 | K75: POR MOD Y MOI | L75: 1 | M75: 4 | N75: 0 | O75: ='LIBRO DIARIO'!G30 -> 979.76925 | P75: =O75-N75 -> 979.76925
B76: ='LIBRO DIARIO'!B36 -> 46031 | C76: POR VARIOS | D76: 1 | E76: 5 | G76: ='LIBRO DIARIO'!G41 -> 583.80799 | H76: =H75+F76-G76 -> 0 | J76: ='LIBRO DIARIO'!B43 -> 46036 | K76: POR MOD Y MOI | L76: 1 | M76: 6 | O76: ='LIBRO DIARIO'!G46 -> 587.86155 | P76: =(P75+O76)-N76 -> 1567.6308
B77: ='LIBRO DIARIO'!B43 -> 46036 | C77: A VARIOS | D77: 1 | E77: 6 | F77: ='LIBRO DIARIO'!F45 -> 350.2848 | H77: =H76+F77-G77 -> 350.2848
B78: ='LIBRO DIARIO'!B52 -> 46036 | C78: POR PRODUCCIÓN. PROCESO | D78: 1 | E78: 7 | G78: ='LIBRO DIARIO'!G57 -> 350.2848 | H78: =H77+F78-G78 -> 0
F81: =SUM(F75:F80) -> 934.09279 | G81: =SUM(G75:G80) -> 934.09279 | H81: =SUM(H75:H80) -> 934.09279 | N81: =SUM(N75:N80) -> 0 | O81: =SUM(O75:O80) -> 1567.6308 | P81: =SUM(P75:P80) -> 2547.4001
B84: Industrias "ALAN SPORT" | J84: Industrias "ALAN SPORT"
B85: LIBRO MAYOR | J85: LIBRO MAYOR
B86: CUENTA | C86: ='LIBRO DIARIO'!C31 -> XIII SUELDO POR PAGAR | G86: No | H86: 13 | J86: CUENTA | K86: ='LIBRO DIARIO'!C32 -> XIV SUELDO POR PAGAR | O86: No | P86: 14
B87: FECHA | C87: DETALLE | D87: F | E87: A | F87: DEBE | G87: HABER | H87: SALDO | J87: FECHA | K87: DETALLE | L87: F | M87: A | N87: DEBE | O87: HABER | P87: SALDO
B88: ='LIBRO DIARIO'!B27 -> 46031 | C88: POR MOD Y MOI | D88: 1 | E88: 4 | F88: 0 | G88: ='LIBRO DIARIO'!G31 -> 377.9974 | H88: =G88-F88 -> 377.9974 | J88: ='LIBRO DIARIO'!B27 -> 46031 | K88: POR MOD Y MOI | L88: 1 | M88: 4 | N88: $ - | O88: ='LIBRO DIARIO'!G32 -> 321.33333 | P88: 979.77
B89: ='LIBRO DIARIO'!B43 -> 46036 | C89: POR MOD Y MOI | D89: 1 | E89: 6 | G89: ='LIBRO DIARIO'!G47 -> 226.79844 | H89: =(H88+G89)-F89 -> 604.79583 | J89: ='LIBRO DIARIO'!B43 -> 46036 | K89: POR MOD Y MOI | L89: 1 | M89: 6 | O89: ='LIBRO DIARIO'!G48 -> 192.8 | P89: =(P88+O89)-N89 -> 1172.57
F94: =SUM(F88:F93) -> 0 | G94: =SUM(G88:G93) -> 604.79583 | H94: =SUM(H88:H93) -> 982.79323 | N94: =SUM(N88:N93) -> 0 | O94: =SUM(O88:O93) -> 514.13333 | P94: =SUM(P88:P93) -> 2152.34
B97: Industrias "ALAN SPORT" | J97: Industrias "ALAN SPORT"
B98: LIBRO MAYOR | J98: LIBRO MAYOR
B99: CUENTA | C99: ='LIBRO DIARIO'!C33 -> VACACIONES | G99: No | H99: 15 | J99: CUENTA | K99: ='LIBRO DIARIO'!C50 -> SUELDOS POR PAGAR | O99: No | P99: 16
B100: FECHA | C100: DETALLE | D100: F | E100: A | F100: DEBE | G100: HABER | H100: SALDO | J100: FECHA | K100: DETALLE | L100: F | M100: A | N100: DEBE | O100: HABER | P100: SALDO
B101: ='LIBRO DIARIO'!B27 -> 46031 | C101: POR MOD Y MOI | D101: 1 | E101: 4 | F101: ='[1]LIBRO DIARIO'!F70 -> 0 | G101: ='LIBRO DIARIO'!G33 -> 188.9987 | H101: =G101-F101 -> 188.9987 | J101: ='LIBRO DIARIO'!B43 -> 46036 | K101: POR MOD Y MOI | L101: 1 | M101: 6 | N101: ='[1]LIBRO DIARIO'!N70 -> 0 | O101: ='LIBRO DIARIO'!G50 -> 2588.3887 | P101: =O101-N101 -> 2588.3887
B102: ='LIBRO DIARIO'!B43 -> 46036 | C102: POR MOD Y MOI | D102: 1 | E102: 6 | G102: ='LIBRO DIARIO'!G49 -> 113.39922 | H102: =(H101+G102)-F102 -> 302.39792
F107: =SUM(F101:F106) -> 0 | G107: =SUM(G101:G106) -> 302.39792 | H107: =SUM(H101:H106) -> 491.39661 | N107: =SUM(N101:N106) -> 0 | O107: =SUM(O101:O106) -> 2588.3887 | P107: =SUM(P101:P106) -> 2588.3887
B110: Industrias "ALAN SPORT" | J110: Industrias "ALAN SPORT"
B111: LIBRO MAYOR | J111: LIBRO MAYOR
B112: CUENTA | C112: ='LIBRO DIARIO'!C60 -> ENERGÍA ELÉCTRICA | G112: No | H112: 17 | J112: CUENTA | K112: ='LIBRO DIARIO'!C61 -> MANTENIMIENTO | O112: No | P112: 18
B113: FECHA | C113: DETALLE | D113: F | E113: A | F113: DEBE | G113: HABER | H113: SALDO | J113: FECHA | K113: DETALLE | L113: F | M113: A | N113: DEBE | O113: HABER | P113: SALDO
B114: ='LIBRO DIARIO'!B59 -> 46036 | C114: A VARIOS | D114: 1 | E114: 8 | F114: ='LIBRO DIARIO'!F60 -> 187.5 | H114: =F114-G114 -> 187.5 | J114: ='LIBRO DIARIO'!B59 -> 46036 | K114: A VARIOS | L114: 1 | M114: 8 | N114: ='LIBRO DIARIO'!F61 -> 281.25 | O114: ='LIBRO DIARIO'!O46 -> 0 | P114: =N114-O114 -> 281.25
B115: ='LIBRO DIARIO'!B67 -> 46036 | C115: POR CIF | D115: 1 | E115: 9 | G115: ='LIBRO DIARIO'!G69 -> 187.5 | H115: =(H114+F115)-G115 -> 0 | J115: ='LIBRO DIARIO'!B67 -> 46036 | K115: POR CIF | L115: 1 | M115: 9 | O115: ='LIBRO DIARIO'!G70 -> 281.25 | P115: =(P114+N115)-O115 -> 0
F120: =SUM(F114:F119) -> 187.5 | G120: =SUM(G114:G119) -> 187.5 | H120: =SUM(H114:H119) -> 187.5 | N120: =SUM(N114:N119) -> 281.25 | O120: =SUM(O114:O119) -> 281.25 | P120: =SUM(P114:P119) -> 281.25
B124: Industrias "ALAN SPORT" | J124: Industrias "ALAN SPORT"
B125: LIBRO MAYOR | J125: LIBRO MAYOR
B126: CUENTA | C126: ='LIBRO DIARIO'!C62 -> SEGUROS DE FÁBRICA | G126: No | H126: 19 | J126: CUENTA | K126: ='LIBRO DIARIO'!C63 -> DEPRECIACIÓN MAQUINARIA | O126: No | P126: 20
B127: FECHA | C127: DETALLE | D127: F | E127: A | F127: DEBE | G127: HABER | H127: SALDO | J127: FECHA | K127: DETALLE | L127: F | M127: A | N127: DEBE | O127: HABER | P127: SALDO
B128: ='LIBRO DIARIO'!B59 -> 46036 | C128: A VARIOS | D128: 1 | E128: 8 | F128: ='LIBRO DIARIO'!F62 -> 131.25 | G128: ='LIBRO DIARIO'!G60 -> 0 | H128: =F128-G128 -> 131.25 | J128: ='LIBRO DIARIO'!B59 -> 46036 | K128: A VARIOS | L128: 1 | M128: 8 | N128: ='LIBRO DIARIO'!F63 -> 218.75 | O128: ='LIBRO DIARIO'!O60 -> 0 | P128: =N128-O128 -> 218.75
B129: ='LIBRO DIARIO'!B67 -> 46036 | C129: POR CIF | D129: 1 | E129: 9 | G129: ='LIBRO DIARIO'!G71 -> 131.25 | H129: =(H128+F129)-G129 -> 0 | J129: ='LIBRO DIARIO'!B67 -> 46036 | K129: POR CIF | L129: 1 | M129: 9 | O129: ='LIBRO DIARIO'!G72 -> 218.75 | P129: =(P128+N129)-O129 -> 0
F134: =SUM(F128:F133) -> 131.25 | G134: =SUM(G128:G133) -> 131.25 | H134: =SUM(H128:H133) -> 131.25 | N134: =SUM(N128:N133) -> 218.75 | O134: =SUM(O128:O133) -> 218.75 | P134: =SUM(P128:P133) -> 218.75
B137: Industrias "ALAN SPORT" | J137: Industrias "ALAN SPORT"
B138: LIBRO MAYOR | J138: LIBRO MAYOR
B139: CUENTA | C139: ='LIBRO DIARIO'!C64 -> CUENTAS POR PAGAR | G139: No | H139: 21 | J139: CUENTA | K139: ='LIBRO DIARIO'!C65 -> DEPRE. ACUM. MAQUINARIA | O139: No | P139: 22
B140: FECHA | C140: DETALLE | D140: F | E140: A | F140: DEBE | G140: HABER | H140: SALDO | J140: FECHA | K140: DETALLE | L140: F | M140: A | N140: DEBE | O140: HABER | P140: SALDO
B141: ='LIBRO DIARIO'!B59 -> 46036 | C141: POR VARIOS | D141: 1 | E141: 8 | F141: ='[1]LIBRO DIARIO'!F110 -> 0 | G141: ='LIBRO DIARIO'!G64 -> 600 | H141: =G141-F141 -> 600 | J141: ='LIBRO DIARIO'!B59 -> 46036 | K141: POR VARIOS | L141: 1 | M141: 8 | N141: ='[1]LIBRO DIARIO'!N110 -> 0 | O141: ='LIBRO DIARIO'!G65 -> 218.75 | P141: =O141-N141 -> 218.75
F147: =SUM(F141:F146) -> 0 | G147: =SUM(G141:G146) -> 600 | H147: =SUM(H141:H146) -> 600 | N147: =SUM(N141:N146) -> 0 | O147: =SUM(O141:O146) -> 218.75 | P147: =SUM(P141:P146) -> 218.75
B151: Industrias "ALAN SPORT" | J151: Industrias "ALAN SPORT"
B152: LIBRO MAYOR | J152: LIBRO MAYOR
B153: CUENTA | C153: ='LIBRO DIARIO'!C68 -> COSTOS INDIRECTOS FÁBRICA | G153: No | H153: 23 | J153: CUENTA | K153: ='LIBRO DIARIO'!C81 -> PRODUCTO TERMINADO OP#100 TS | O153: No | P153: 24
B154: FECHA | C154: DETALLE | D154: F | E154: A | F154: DEBE | G154: HABER | H154: SALDO | J154: FECHA | K154: DETALLE | L154: F | M154: A | N154: DEBE | O154: HABER | P154: SALDO
B155: ='LIBRO DIARIO'!B67 -> 46036 | C155: A VARIOS | D155: 1 | E155: 9 | F155: ='LIBRO DIARIO'!F68 -> 818.75 | H155: =F155-G155 -> 818.75 | J155: ='LIBRO DIARIO'!B80 -> 46036 | K155: A VARIOS | L155: 1 | M155: 11 | N155: ='LIBRO DIARIO'!F81 -> 21498.695 | O155: ='LIBRO DIARIO'!G79 -> 0 | P155: =N155-O155 -> 21498.695
B156: ='LIBRO DIARIO'!B74 -> 46036 | C156: POR PRODUCCIÓN. PROCESO | D156: 1 | E156: 10 | G156: ='LIBRO DIARIO'!G78 -> 818.75 | H156: =(H155+F156)-G156 -> 0 | J156: ='LIBRO DIARIO'!B92 -> 46036 | K156: POR VENTA | L156: 1 | M156: 12.1 | O156: ='LIBRO DIARIO'!G94 -> 21498.695 | P156: =P155+N156-O156 -> 0
...

Sheet HOJA DE COSTOS
B3: INDUSTRIAS "ALAN SPORT" | H3: INDUSTRIAS "ALAN SPORT" | N3: INDUSTRIAS "ALAN SPORT"
B4: HOJA DE COSTOS | H4: HOJA DE COSTOS | N4: HOJA DE COSTOS
B5: NÚMERO: | D5: 10 | H5: NÚMERO: | J5: 10 | N5: NÚMERO: | P5: 10
B6: ORDEN DE PRODUCCIÓN: | D6: 100 | H6: ORDEN DE PRODUCCIÓN: | J6: 100 | N6: ORDEN DE PRODUCCIÓN: | P6: 100
B7: CLIENTE: | D7: TOMY | H7: CLIENTE: | J7: TOMY | N7: CLIENTE: | P7: TOMY
B8: PRODUCTO: | D8: ='ORDEN P'!C10 -> CAMISETA S | H8: PRODUCTO: | J8: ='ORDEN P'!C11 -> CAMISETA M | N8: PRODUCTO: | P8: ='ORDEN P'!C12 -> CAMISETA L
B9: CANTIDAD: | D9: ='ORDEN P'!B10 -> 4000 | H9: CANTIDAD: | J9: ='ORDEN P'!B11 -> 6000 | N9: CANTIDAD: | P9: ='ORDEN P'!B12 -> 5000
B10: FECHA DE INICIO: | D10: 46027 | H10: FECHA DE INICIO: | J10: 46027 | N10: FECHA DE INICIO: | P10: 46027
B11: FECHA TERMINO: | D11: =KARDEX!B116 -> 46036 | H11: FECHA TERMINO: | J11: 46036 | N11: FECHA TERMINO: | P11: =KARDEX!N116 -> 0
B13: MATERIA PRIMA DIRECTA | H13: MATERIA PRIMA DIRECTA | N13: MATERIA PRIMA DIRECTA
B14: FACHA | C14: DETALLE | D14: CANTIDAD | E14: V.UNITARIO | F14: V.TOTAL | H14: FACHA | I14: DETALLE | J14: CANTIDAD | K14: V.UNITARIO | L14: V.TOTAL | N14: FACHA | O14: DETALLE | P14: CANTIDAD | Q14: V.UNITARIO | R14: V.TOTAL
B15: =KARDEX!B11 -> 46027 | C15: =KARDEX!C5 -> TELA PIQUET | D15: ='HOJA DE COSTOS'!D9 -> 4000 | E15: =F15/D15 -> 3.619311 | F15: =KARDEX!I11 -> 14477.244 | H15: =B15 -> 46027 | I15: =C15 -> TELA PIQUET | J15: ='HOJA DE COSTOS'!J9 -> 6000 | K15: =L15/J15 -> 4.0717249 | L15: =KARDEX!I12 -> 24430.349 | N15: =B15 -> 46027 | O15: =C15 -> TELA PIQUET | P15: ='HOJA DE COSTOS'!P9 -> 5000 | Q15: =R15/P15 -> 4.9765526 | R15: =KARDEX!I13 -> 24882.763
B16: =KARDEX!B27 -> 46027 | C16: =KARDEX!C21 -> CUELLOS | D16: =D9 -> 4000 | E16: =F16/D16 -> 0.54285714 | F16: =KARDEX!I27 -> 2171.4286 | H16: =B16 -> 46027 | I16: =C16 -> CUELLOS | J16: =J9 -> 6000 | K16: =L16/J16 -> 0.54285714 | L16: =KARDEX!I28 -> 3257.1429 | N16: =B16 -> 46027 | O16: =C16 -> CUELLOS | P16: =P9 -> 5000 | Q16: =R16/P16 -> 0.54285714 | R16: =KARDEX!I29 -> 2714.2857
B17: =KARDEX!B43 -> 46027 | C17: =KARDEX!C37 -> PUÑOS | D17: =D9 -> 4000 | E17: =F17/D17 -> 0.4352381 | F17: =KARDEX!I43 -> 1740.9524 | H17: =B17 -> 46027 | I17: =C17 -> PUÑOS | J17: =J9 -> 6000 | K17: =L17/J17 -> 0.4352381 | L17: =KARDEX!I44 -> 2611.4286 | N17: =B17 -> 46027 | O17: =C17 -> PUÑOS | P17: =P9 -> 5000 | Q17: =R17/P17 -> 0.4352381 | R17: =KARDEX!I45 -> 2176.1905
B18: =KARDEX!B59 -> 46027 | C18: =KARDEX!C53 -> BOTÓN | D18: =D9 -> 4000 | E18: =F18/D18 -> 0.10047619 | F18: =KARDEX!I59 -> 401.90476 | H18: =B18 -> 46027 | I18: =C18 -> BOTÓN | J18: =J9 -> 6000 | K18: =L18/J18 -> 0.10047619 | L18: =KARDEX!I60 -> 602.85714 | N18: =B18 -> 46027 | O18: =C18 -> BOTÓN | P18: =P9 -> 5000 | Q18: =R18/P18 -> 0.10047619 | R18: =KARDEX!I61 -> 502.38095
E19: SUBTOTAL: | F19: =SUM(F15:F18) -> 18791.53 | K19: SUBTOTAL: | L19: =SUM(L15:L18) -> 30901.778 | Q19: SUBTOTAL: | R19: =SUM(R15:R18) -> 30275.62
B21: MATERIA DE OBRA DIRECTA | H21: MATERIA DE OBRA DIRECTA | N21: MATERIA DE OBRA DIRECTA
B22: FACHA | C22: DETALLE | D22: CANTIDAD | E22: V.UNITARIO | F22: V.TOTAL | H22: FACHA | I22: DETALLE | J22: CANTIDAD | K22: V.UNITARIO | L22: V.TOTAL | N22: FACHA | O22: DETALLE | P22: CANTIDAD | Q22: V.UNITARIO | R22: V.TOTAL
B23: =MAYORIZACIÓN!J61 -> 46031 | C23: DEL 5 AL 9 DE ENERO | D23: =D9 -> 4000 | E23: =F23/D23 -> 0.34989199 | F23: ='LIBRO DIARIO'!G40*25% -> 1399.568 | H23: =B23 -> 46031 | I23: DEL 5 AL 9 DE ENERO | J23: =J9 -> 6000 | K23: =L23/J23 -> 0.37321812 | L23: ='LIBRO DIARIO'!G40*40% -> 2239.3087 | N23: =B23 -> 46031 | O23: DEL 5 AL 9 DE ENERO | P23: =P9 -> 5000 | Q23: =R23/P23 -> 0.39187903 | R23: ='LIBRO DIARIO'!G40*35% -> 1959.3951
B24: ='LIBRO DIARIO'!B43 -> 46036 | C24: DEL 12 AL 14 DE ENERO | D24: =D9 -> 4000 | E24: =F24/D24 -> 0.20993519 | F24: ='LIBRO DIARIO'!G56*25% -> 839.74078 | H24: =B24 -> 46036 | I24: DEL 12 AL 14 DE ENERO | J24: =J9 -> 6000 | K24: =L24/J24 -> 0.22393087 | L24: ='LIBRO DIARIO'!F44*40% -> 1343.5852 | N24: =B24 -> 46036 | O24: DEL 12 AL 14 DE ENERO | P24: =P9 -> 5000 | Q24: =R24/P24 -> 0.23512742 | R24: ='LIBRO DIARIO'!G56*35% -> 1175.6371
E25: SUBTOTAL: | F25: =SUM(F23:F24) -> 2239.3087 | K25: SUBTOTAL: | L25: =SUM(L23:L24) -> 3582.894 | Q25: SUBTOTAL: | R25: =SUM(R23:R24) -> 3135.0322
B27: COSTOS INDIRECTOS DE FÀBRICA | H27: COSTOS INDIRECTOS DE FÀBRICA | N27: COSTOS INDIRECTOS DE FÀBRICA
B28: FACHA | C28: DETALLE | D28: CANTIDAD | E28: V.UNITARIO | F28: V.TOTAL | H28: FACHA | I28: DETALLE | J28: CANTIDAD | K28: V.UNITARIO | L28: V.TOTAL | N28: FACHA | O28: DETALLE | P28: CANTIDAD | Q28: V.UNITARIO | R28: V.TOTAL
B29: =KARDEX!B75 -> 46027 | C29: =KARDEX!C69 -> HILO | D29: =D9 -> 4000 | E29: =F29/D29 -> 0.004 | F29: =KARDEX!I75 -> 16 | H29: =B29 -> 46027 | I29: =C29 -> HILO | J29: =J9 -> 6000 | K29: =L29/J29 -> 0.005 | L29: =KARDEX!I76 -> 30 | N29: =B29 -> 46027 | O29: HILO | P29: =P9 -> 5000 | Q29: =R29/P29 -> 0.006 | R29: =KARDEX!I77 -> 30
B30: =MAYORIZACIÓN!B75 -> 46031 | C30: MOI | D30: =D9 -> 4000 | E30: =F30/D30 -> 0.036488 | F30: ='LIBRO DIARIO'!F29*25% -> 145.952 | H30: =B30 -> 46031 | I30: =C30 -> MOI | J30: =J9 -> 6000 | K30: =L30/J30 -> 0.038920533 | L30: ='LIBRO DIARIO'!F29*40% -> 233.5232 | N30: =B30 -> 46031 | O30: MOI | P30: =P9 -> 5000 | Q30: =R30/P30 -> 0.04086656 | R30: ='LIBRO DIARIO'!F29*35% -> 204.3328
B31: ='LIBRO DIARIO'!B43 -> 46036 | C31: MOI | D31: =D9 -> 4000 | E31: =F31/D31 -> 0.0218928 | F31: ='LIBRO DIARIO'!F45*25% -> 87.571199 | H31: =B31 -> 46036 | I31: =C31 -> MOI | J31: =J9 -> 6000 | K31: =L31/J31 -> 0.02335232 | L31: ='LIBRO DIARIO'!F45*40% -> 140.11392 | N31: =B31 -> 46036 | O31: =C31 -> MOI | P31: =P9 -> 5000 | Q31: =R31/P31 -> 0.024519936 | R31: ='LIBRO DIARIO'!F45*35% -> 122.59968
B32: ='LIBRO DIARIO'!B43 -> 46036 | C32: =CÁLCULOS!B64 -> ENERGÍA ELÉCTRICA | D32: =D9 -> 4000 | E32: =F32/D32 -> 0.0125 | F32: =CÁLCULOS!G64 -> 50 | H32: =B32 -> 46036 | I32: =C32 -> ENERGÍA ELÉCTRICA | J32: =J9 -> 6000 | K32: =L32/J32 -> 0.0125 | L32: =CÁLCULOS!H64 -> 75 | N32: =B32 -> 46036 | O32: =C32 -> ENERGÍA ELÉCTRICA | P32: =P9 -> 5000 | Q32: =R32/P32 -> 0.0125 | R32: =CÁLCULOS!I64 -> 62.5
B33: ='LIBRO DIARIO'!B43 -> 46036 | C33: =CÁLCULOS!B65 -> MANTENIMIENTO | D33: =D9 -> 4000 | E33: =F33/D33 -> 0.01875 | F33: =CÁLCULOS!G65 -> 75 | H33: =B33 -> 46036 | I33: =C33 -> MANTENIMIENTO | J33: =J9 -> 6000 | K33: =L33/J33 -> 0.01875 | L33: =CÁLCULOS!H65 -> 112.5 | N33: =B33 -> 46036 | O33: =C33 -> MANTENIMIENTO | P33: =P9 -> 5000 | Q33: =R33/P33 -> 0.01875 | R33: =CÁLCULOS!I65 -> 93.75
B34: ='LIBRO DIARIO'!B43 -> 46036 | C34: =CÁLCULOS!B66 -> SEGUROS DE FÁBRICA | D34: =D9 -> 4000 | E34: =F34/D34 -> 0.00875 | F34: =CÁLCULOS!G66 -> 35 | H34: =B34 -> 46036 | I34: =C34 -> SEGUROS DE FÁBRICA | J34: =J9 -> 6000 | K34: =L34/J34 -> 0.00875 | L34: =CÁLCULOS!H66 -> 52.5 | N34: =B34 -> 46036 | O34: =C34 -> SEGUROS DE FÁBRICA | P34: =P9 -> 5000 | Q34: =R34/P34 -> 0.00875 | R34: =CÁLCULOS!I66 -> 43.75
B35: ='LIBRO DIARIO'!B43 -> 46036 | C35: =CÁLCULOS!B67 -> DEPRECIACIÓN MAQUINARIA | D35: =D9 -> 4000 | E35: =F35/D35 -> 0.014583333 | F35: =CÁLCULOS!G67 -> 58.333333 | H35: =B35 -> 46036 | I35: =C35 -> DEPRECIACIÓN MAQUINARIA | J35: =J9 -> 6000 | K35: =L35/J35 -> 0.014583333 | L35: =CÁLCULOS!H67 -> 87.5 | N35: =B35 -> 46036 | O35: =C35 -> DEPRECIACIÓN MAQUINARIA | P35: =P9 -> 5000 | Q35: =R35/P35 -> 0.014583333 | R35: =CÁLCULOS!I67 -> 72.916667
E36: SUBTOTAL: | F36: =SUM(F29:F35) -> 467.85653 | K36: SUBTOTAL: | L36: =SUM(L29:L35) -> 731.13712 | Q36: SUBTOTAL: | R36: =SUM(R29:R35) -> 629.84914
C38: COSTO TOTAL DE PRODUCCIÓN: | F38: =F19+F25+F36 -> 21498.695 | I38: COSTO TOTAL DE PRODUCCIÓN: | L38: =L19+L25+L36 -> 35215.809 | O38: COSTO TOTAL DE PRODUCCIÓN: | R38: =R19+R25+R36 -> 34040.502
C39: UNIDADES PRODUCIDAS: | F39: =D9 -> 4000 | I39: UNIDADES PRODUCIDAS: | L39: =J9 -> 6000 | O39: UNIDADES PRODUCIDAS: | R39: =P9 -> 5000
C40: COSTO UNITARIO: | F40: =F38/F39 -> 5.3746738 | I40: COSTO UNITARIO: | L40: =L38/L39 -> 5.8693015 | O40: COSTO UNITARIO: | R40: =R38/R39 -> 6.8081004
B44: INDUSTRIAS "ALAN SPORT"
B45: HOJA DE COSTOS
B46: NÚMERO: | D46: 11
B47: ORDEN DE PRODUCCIÓN: | D47: ='ORDEN P'!G4 -> 101
B48: CLIENTE: | D48: ='ORDEN P'!G5 -> TEXPAX
B49: PRODUCTO: | D49: ='ORDEN P'!G10 -> CAMISETA S
B50: CANTIDAD: | D50: ='ORDEN P'!F10 -> 5000
B51: FECHA DE INICIO: | D51: ='ORDEN P'!G6 -> 46037
B52: FECHA TERMINO: | D52: ='LIBRO DIARIO'!B158 -> 46050
B54: MATERIA PRIMA DIRECTA
B55: FACHA | C55: DETALLE | D55: CANTIDAD | E55: V.UNITARIO | F55: V.TOTAL
B56: =KARDEX!B15 -> 46037 | C56: =KARDEX!C5 -> TELA PIQUET | D56: =$D$50 -> 5000 | E56: =F56/D56 -> 3.9650077 | F56: =KARDEX!I15 -> 19825.038
B57: =KARDEX!B31 -> 46037 | C57: =KARDEX!C21 -> CUELLOS | D57: =$D$50 -> 5000 | E57: =F57/D57 -> 0.59065934 | F57: =KARDEX!I31 -> 2953.2967
B58: =KARDEX!B47 -> 46037 | C58: =KARDEX!C37 -> PUÑOS | D58: =$D$50 -> 5000 | E58: =F58/D58 -> 0.47274725 | F58: =KARDEX!I47 -> 2363.7363
B59: =KARDEX!B63 -> 46037 | C59: =KARDEX!C53 -> BOTÓN | D59: =$D$50 -> 5000 | E59: =F59/D59 -> 0.11626374 | F59: =KARDEX!I63 -> 581.31868
E60: SUBTOTAL: | F60: =SUM(F56:F59) -> 25723.39
B62: MANO DE OBRA DIRECTA
B63: FACHA | C63: DETALLE | D63: CANTIDAD | E63: V.UNITARIO | F63: V.TOTAL
B64: ='LIBRO DIARIO'!B110 -> 46038 | C64: DEL 15 AL 16 DE ENERO | D64: =$D$50 -> 5000 | E64: =F64/D64 -> 0.11196544 | F64: ='LIBRO DIARIO'!G123*25% -> 559.82718
B65: ='LIBRO DIARIO'!B126 -> 46045 | C65: DEL 19 AL 23 DE ENERO | D65: =$D$50 -> 5000 | E65: =F65/D65 -> 0.27991359 | F65: ='LIBRO DIARIO'!G139*25% -> 1399.568
B66: ='LIBRO DIARIO'!B142 -> 46050 | C66: DEL 26 AL 28 DE ENERO | D66: =$D$50 -> 5000 | E66: =F66/D66 -> 0.16794816 | F66: ='LIBRO DIARIO'!G155*25% -> 839.74078
E67: SUBTOTAL: | F67: =SUM(F64:F66) -> 2799.1359
B69: COSTOS INDIRECTOS DE FÀBRICA
B70: FACHA | C70: DETALLE | D70: CANTIDAD | E70: V.UNITARIO | F70: V.TOTAL
B71: =KARDEX!B79 -> 46037 | C71: =KARDEX!C69 -> HILO | D71: =$D$50 -> 5000 | E71: =F71/D71 -> 0.004 | F71: =KARDEX!I79 -> 20
B72: ='LIBRO DIARIO'!B110 -> 46038 | C72: MOI | D72: =$D$50 -> 5000 | E72: =F72/D72 -> 0.01167616 | F72: ='LIBRO DIARIO'!F112*25% -> 58.380799
B73: ='LIBRO DIARIO'!B126 -> 46045 | C73: MOI | D73: =$D$50 -> 5000 | E73: =F73/D73 -> 0.0291904 | F73: ='LIBRO DIARIO'!F128*25% -> 145.952
B74: ='LIBRO DIARIO'!B142 -> 46050 | C74: MOI | D74: =$D$50 -> 5000 | E74: =F74/D74 -> 0.01751424 | F74: ='LIBRO DIARIO'!F144*25% -> 87.571199
B75: ='LIBRO DIARIO'!B158 -> 46050 | C75: =CÁLCULOS!B141 -> ENERGÍA ELÉCTRICA | D75: =$D$50 -> 5000 | E75: =F75/D75 -> 0.0125 | F75: =CÁLCULOS!G141 -> 62.5
B76: ='LIBRO DIARIO'!B158 -> 46050 | C76: =CÁLCULOS!B142 -> MANTENIMIENTO | D76: =$D$50 -> 5000 | E76: =F76/D76 -> 0.01875 | F76: =CÁLCULOS!G142 -> 93.75
B77: ='LIBRO DIARIO'!B158 -> 46050 | C77: =CÁLCULOS!B143 -> SEGUROS DE FÁBRICA | D77: =$D$50 -> 5000 | E77: =F77/D77 -> 0.00875 | F77: =CÁLCULOS!G143 -> 43.75
B78: ='LIBRO DIARIO'!B158 -> 46050 | C78: =CÁLCULOS!B144 -> DEPRECIACIÓN MAQUINARIA | D78: =$D$50 -> 5000 | E78: =F78/D78 -> 0.014583333 | F78: =CÁLCULOS!G144 -> 72.916667
E79: SUBTOTAL: | F79: =SUM(F71:F78) -> 584.82066
C81: COSTO TOTAL DE PRODUCCIÓN: | F81: =F60+F67+F79 -> 29107.346
C82: UNIDADES PRODUCIDAS: | F82: =$D$50 -> 5000
C83: COSTO UNITARIO: | F83: =F81/F82 -> 5.8214693

Sheet KARDEX
B2: INDUSTRIAS "ALAN SPORT"
B3: KARDEX
B5: PRODUCTO: | C5: TELA PIQUET
B6: UNIDAD MEDIA: METROS | F6: MÉTODO: | H6: PROMEDIO | K6: No. | L6: 1
D7: ENTRADAS | G7: SALIDAS | J7: SALDOS
B8: FECHA | C8: DETALLE | D8: CANT. | E8: V.UNI | F8: V.TOTAL | G8: CANT. | H8: V.UNI | I8: V.TOTAL | J8: CANT. | K8: V.UNI | L8: V.TOTAL
B9: ='LIBRO DIARIO'!B7 -> 46027 | C9: SITUACIÓN INICIA DE LA INDUSTRIA | D9: 4500 | E9: 4.2 | F9: =D9*E9 -> 18900 | J9: =D9-G9 -> 4500 | K9: =L9/J9 -> 4.2 | L9: =F9-I9 -> 18900
B10: 46027 | C10: COMPRA SEGÙN FACTURA PARA OP#100 | D10: =CÁLCULOS!J9 -> 15216 | E10: =E9*1.1 -> 4.62 | F10: =D10*E10 -> 70297.92 | J10: =J9+D10-G10 -> 19716 | K10: =L10/J10 -> 4.5241388 | L10: =L9+F10-I10 -> 89197.92
B11: 46027 | C11: ENVIO A PRODUCCIÓN OP#100 TS | G11: =CÁLCULOS!F5 -> 3200 | H11: =K10 -> 4.5241388 | I11: =G11*H11 -> 14477.244 | J11: =J10+D11-G11 -> 16516 | K11: =L11/J11 -> 4.5241388 | L11: =L10+F11-I11 -> 74720.676
B12: 46027 | C12: ENVIO A PRODUCCIÓN OP#100 TM | G12: =CÁLCULOS!F6 -> 5400 | H12: =K11 -> 4.5241388 | I12: =G12*H12 -> 24430.349 | J12: =J11+D12-G12 -> 11116 | K12: =L12/J12 -> 4.5241388 | L12: =L11+F12-I12 -> 50290.327
B13: 46027 | C13: ENVIO A PRODUCCIÓN OP#100 TL | G13: =CÁLCULOS!F7 -> 5500 | H13: =K12 -> 4.5241388 | I13: =G13*H13 -> 24882.763 | J13: =J12+D13-G13 -> 5616 | K13: =L13/J13 -> 4.5241388 | L13: =L12+F13-I13 -> 25407.563
B14: ='LIBRO DIARIO'!B98 -> 46037 | C14: COMPRA SEGÙN FACTURA PARA OP#101 | D14: =CÁLCULOS!E86 -> 19300 | E14: =E10*1.1 -> 5.082 | F14: =D14*E14 -> 98082.6 | J14: =J13+D14-G14 -> 24916 | K14: =L14/J14 -> 4.9562596 | L14: =L13+F14-I14 -> 123490.16
B15: ='LIBRO DIARIO'!B98 -> 46037 | C15: ENVIO A PRODUCCIÓN OP#101 TS | G15: =CÁLCULOS!F82 -> 4000 | H15: =K14 -> 4.9562596 | I15: =G15*H15 -> 19825.038 | J15: =J14+D15-G15 -> 20916 | K15: =L15/J15 -> 4.9562596 | L15: =L14+F15-I15 -> 103665.13
B16: ='LIBRO DIARIO'!B98 -> 46037 | C16: ENVIO A PRODUCCIÓN OP#101 TM | G16: =CÁLCULOS!F83 -> 5400 | H16: =K15 -> 4.9562596 | I16: =G16*H16 -> 26763.802 | J16: =J15+D16-G16 -> 15516 | K16: =L16/J16 -> 4.9562596 | L16: =L15+F16-I16 -> 76901.323
B17: ='LIBRO DIARIO'!B98 -> 46037 | C17: ENVIO A PRODUCCIÓN OP#101 TL | G17: =CÁLCULOS!F84 -> 9900 | H17: =K16 -> 4.9562596 | I17: =G17*H17 -> 49066.97 | J17: =J16+D17-G17 -> 5616 | K17: =L17/J17 -> 4.9562596 | L17: =L16+F17-I17 -> 27834.354
B21: PRODUCTO: | C21: CUELLOS
B22: UNIDAD MEDIA: UNITARIO | F22: MÉTODO: | H22: PROMEDIO | K22: No. | L22: 2
D23: ENTRADAS | G23: SALIDAS | J23: SALDOS
B24: FECHA | C24: DETALLE | D24: CANT. | E24: V.UNI | F24: V.TOTAL | G24: CANT. | H24: V.UNI | I24: V.TOTAL | J24: CANT. | K24: V.UNI | L24: V.TOTAL
B25: ='LIBRO DIARIO'!B7 -> 46027 | C25: SITUACIÓN INICIA DE LA INDUSTRIA | D25: 3000 | E25: 0.5 | F25: =D25*E25 -> 1500 | J25: =D25-G25 -> 3000 | K25: =L25/J25 -> 0.5 | L25: =F25-I25 -> 1500
B26: 46027 | C26: COMPRA SEGÙN FACTURA PARA OP#100 | D26: =CÁLCULOS!J18 -> 18000 | E26: =E25*1.1 -> 0.55 | F26: =D26*E26 -> 9900 | J26: =J25+D26-G26 -> 21000 | K26: =L26/J26 -> 0.54285714 | L26: =L25+F26-I26 -> 11400
B27: 46027 | C27: ENVIO A PRODUCCIÓN OP#100 TS | G27: =CÁLCULOS!E15 -> 4000 | H27: =K26 -> 0.54285714 | I27: =G27*H27 -> 2171.4286 | J27: =J26+D27-G27 -> 17000 | K27: =L27/J27 -> 0.54285714 | L27: =L26+F27-I27 -> 9228.5714
B28: 46027 | C28: ENVIO A PRODUCCIÓN OP#100 TM | G28: =CÁLCULOS!E16 -> 6000 | H28: =K27 -> 0.54285714 | I28: =G28*H28 -> 3257.1429 | J28: =J27+D28-G28 -> 11000 | K28: =L28/J28 -> 0.54285714 | L28: =L27+F28-I28 -> 5971.4286
B29: 46027 | C29: ENVIO A PRODUCCIÓN OP#100 TL | G29: =CÁLCULOS!E17 -> 5000 | H29: =K28 -> 0.54285714 | I29: =G29*H29 -> 2714.2857 | J29: =J28+D29-G29 -> 6000 | K29: =L29/J29 -> 0.54285714 | L29: =L28+F29-I29 -> 3257.1429
B30: ='LIBRO DIARIO'!B98 -> 46037 | C30: COMPRA SEGÙN FACTURA PARA OP#101 | D30: =CÁLCULOS!J95 -> 20000 | E30: =E26*1.1 -> 0.605 | F30: =D30*E30 -> 12100 | J30: =J29+D30-G30 -> 26000 | K30: =L30/J30 -> 0.59065934 | L30: =L29+F30-I30 -> 15357.143
B31: ='LIBRO DIARIO'!B98 -> 46037 | C31: ENVIO A PRODUCCIÓN OP#100 TS | G31: =CÁLCULOS!E92 -> 5000 | H31: =K30 -> 0.59065934 | I31: =G31*H31 -> 2953.2967 | J31: =J30+D31-G31 -> 21000 | K31: =L31/J31 -> 0.59065934 | L31: =L30+F31-I31 -> 12403.846
B32: ='LIBRO DIARIO'!B98 -> 46037 | C32: ENVIO A PRODUCCIÓN OP#100 TM | G32: =CÁLCULOS!E93 -> 6000 | H32: =K31 -> 0.59065934 | I32: =G32*H32 -> 3543.956 | J32: =J31+D32-G32 -> 15000 | K32: =L32/J32 -> 0.59065934 | L32: =L31+F32-I32 -> 8859.8901
B33: ='LIBRO DIARIO'!B98 -> 46037 | C33: ENVIO A PRODUCCIÓN OP#100 TL | G33: =CÁLCULOS!E94 -> 9000 | H33: =K32 -> 0.59065934 | I33: =G33*H33 -> 5315.9341 | J33: =J32+D33-G33 -> 6000 | K33: =L33/J33 -> 0.59065934 | L33: =L32+F33-I33 -> 3543.956
B37: PRODUCTO: | C37: PUÑOS
B38: UNIDAD MEDIA: UNITARIO | F38: MÉTODO: | H38: PROMEDIO | K38: No. | L38: 3
D39: ENTRADAS | G39: SALIDAS | J39: SALDOS
B40: FECHA | C40: DETALLE | D40: CANT. | E40: V.UNI | F40: V.TOTAL | G40: CANT. | H40: V.UNI | I40: V.TOTAL | J40: CANT. | K40: V.UNI | L40: V.TOTAL
B41: ='LIBRO DIARIO'!B7 -> 46027 | C41: SITUACIÓN INICIA DE LA INDUSTRIA | D41: 5000 | E41: 0.2 | F41: =D41*E41 -> 1000 | J41: =D41-G41 -> 5000 | K41: =L41/J41 -> 0.2 | L41: =F41-I41 -> 1000
B42: 46027 | C42: COMPRA SEGÙN FACTURA PARA OP#100 | D42: =CÁLCULOS!J27 -> 37000 | E42: =E41*1.1 -> 0.22 | F42: =D42*E42 -> 8140 | J42: =J41+D42-G42 -> 42000 | K42: =L42/J42 -> 0.21761905 | L42: =L41+F42-I42 -> 9140
B43: 46027 | C43: ENVIO A PRODUCCIÓN OP#100 TS | G43: =CÁLCULOS!E24 -> 8000 | H43: =K42 -> 0.21761905 | I43: =G43*H43 -> 1740.9524 | J43: =J42+D43-G43 -> 34000 | K43: =L43/J43 -> 0.21761905 | L43: =L42+F43-I43 -> 7399.0476
B44: 46027 | C44: ENVIO A PRODUCCIÓN OP#100 TM | G44: =CÁLCULOS!E25 -> 12000 | H44: =K43 -> 0.21761905 | I44: =G44*H44 -> 2611.4286 | J44: =J43+D44-G44 -> 22000 | K44: =L44/J44 -> 0.21761905 | L44: =L43+F44-I44 -> 4787.619
B45: 46027 | C45: ENVIO A PRODUCCIÓN OP#100 TL | G45: =CÁLCULOS!E26 -> 10000 | H45: =K44 -> 0.21761905 | I45: =G45*H45 -> 2176.1905 | J45: =J44+D45-G45 -> 12000 | K45: =L45/J45 -> 0.21761905 | L45: =L44+F45-I45 -> 2611.4286
B46: ='LIBRO DIARIO'!B98 -> 46037 | C46: COMPRA SEGÙN FACTURA PARA OP#101 | D46: =CÁLCULOS!J104 -> 40000 | E46: =E42*1.1 -> 0.242 | F46: =D46*E46 -> 9680 | J46: =J45+D46-G46 -> 52000 | K46: =L46/J46 -> 0.23637363 | L46: =L45+F46-I46 -> 12291.429
B47: ='LIBRO DIARIO'!B98 -> 46037 | C47: ENVIO A PRODUCCIÓN OP#100 TS | G47: =CÁLCULOS!E101 -> 10000 | H47: =K46 -> 0.23637363 | I47: =G47*H47 -> 2363.7363 | J47: =J46+D47-G47 -> 42000 | K47: =L47/J47 -> 0.23637363 | L47: =L46+F47-I47 -> 9927.6923
B48: ='LIBRO DIARIO'!B98 -> 46037 | C48: ENVIO A PRODUCCIÓN OP#100 TM | G48: =CÁLCULOS!E102 -> 12000 | H48: =K47 -> 0.23637363 | I48: =G48*H48 -> 2836.4835 | J48: =J47+D48-G48 -> 30000 | K48: =L48/J48 -> 0.23637363 | L48: =L47+F48-I48 -> 7091.2088
B49: ='LIBRO DIARIO'!B98 -> 46037 | C49: ENVIO A PRODUCCIÓN OP#100 TL | G49: =CÁLCULOS!E103 -> 18000 | H49: =K48 -> 0.23637363 | I49: =G49*H49 -> 4254.7253 | J49: =J48+D49-G49 -> 12000 | K49: =L49/J49 -> 0.23637363 | L49: =L48+F49-I49 -> 2836.4835
B53: PRODUCTO: | C53: BOTÓN
B54: UNIDAD MEDIA: UNITARIO | F54: MÉTODO: | H54: PROMEDIO | K54: No. | L54: 4
D55: ENTRADAS | G55: SALIDAS | J55: SALDOS
B56: FECHA | C56: DETALLE | D56: CANT. | E56: V.UNI | F56: V.TOTAL | G56: CANT. | H56: V.UNI | I56: V.TOTAL | J56: CANT. | K56: V.UNI | L56: V.TOTAL
B57: ='LIBRO DIARIO'!B7 -> 46027 | C57: SITUACIÓN INICIA DE LA INDUSTRIA | D57: 40000 | E57: 0.05 | F57: =D57*E57 -> 2000 | J57: =D57-G57 -> 40000 | K57: =L57/J57 -> 0.05 | L57: =F57-I57 -> 2000
B58: 46027 | C58: COMPRA SEGÙN FACTURA PARA OP#100 | D58: =CÁLCULOS!J36 -> 2000 | E58: =E57*1.1 -> 0.055 | F58: =D58*E58 -> 110 | J58: =J57+D58-G58 -> 42000 | K58: =L58/J58 -> 0.050238095 | L58: =L57+F58-I58 -> 2110
B59: 46027 | C59: ENVIO A PRODUCCIÓN OP#100 TS | G59: =CÁLCULOS!E33 -> 8000 | H59: =K58 -> 0.050238095 | I59: =G59*H59 -> 401.90476 | J59: =J58+D59-G59 -> 34000 | K59: =L59/J59 -> 0.050238095 | L59: =L58+F59-I59 -> 1708.0952
B60: 46027 | C60: ENVIO A PRODUCCIÓN OP#100 TM | G60: =CÁLCULOS!E34 -> 12000 | H60: =K59 -> 0.050238095 | I60: =G60*H60 -> 602.85714 | J60: =J59+D60-G60 -> 22000 | K60: =L60/J60 -> 0.050238095 | L60: =L59+F60-I60 -> 1105.2381
B61: 46027 | C61: ENVIO A PRODUCCIÓN OP#100 TL | G61: =CÁLCULOS!E35 -> 10000 | H61: =K60 -> 0.050238095 | I61: =G61*H61 -> 502.38095 | J61: =J60+D61-G61 -> 12000 | K61: =L61/J61 -> 0.050238095 | L61: =L60+F61-I61 -> 602.85714
B62: ='LIBRO DIARIO'!B98 -> 46037 | C62: COMPRA SEGÙN FACTURA PARA OP#101 | D62: =CÁLCULOS!J113 -> 40000 | E62: =E58*1.1 -> 0.0605 | F62: =D62*E62 -> 2420 | J62: =J61+D62-G62 -> 52000 | K62: =L62/J62 -> 0.058131868 | L62: =L61+F62-I62 -> 3022.8571
B63: ='LIBRO DIARIO'!B98 -> 46037 | C63: ENVIO A PRODUCCIÓN OP#100 TS | G63: =CÁLCULOS!E110 -> 10000 | H63: =K62 -> 0.058131868 | I63: =G63*H63 -> 581.31868 | J63: =J62+D63-G63 -> 42000 | K63: =L63/J63 -> 0.058131868 | L63: =L62+F63-I63 -> 2441.5385
B64: ='LIBRO DIARIO'!B98 -> 46037 | C64: ENVIO A PRODUCCIÓN OP#100 TM | G64: =CÁLCULOS!E111 -> 12000 | H64: =K63 -> 0.058131868 | I64: =G64*H64 -> 697.58242 | J64: =J63+D64-G64 -> 30000 | K64: =L64/J64 -> 0.058131868 | L64: =L63+F64-I64 -> 1743.956
B65: ='LIBRO DIARIO'!B98 -> 46037 | C65: ENVIO A PRODUCCIÓN OP#100 TL | G65: =CÁLCULOS!E112 -> 18000 | H65: =K64 -> 0.058131868 | I65: =G65*H65 -> 1046.3736 | J65: =J64+D65-G65 -> 12000 | K65: =L65/J65 -> 0.058131868 | L65: =L64+F65-I65 -> 697.58242
B69: PRODUCTO: | C69: HILO
B70: UNIDAD MEDIA: METRO | F70: MÉTODO: | H70: PROMEDIO | K70: No. | L70: 5
D71: ENTRADAS | G71: SALIDAS | J71: SALDOS
B72: FECHA | C72: DETALLE | D72: CANT. | E72: V.UNI | F72: V.TOTAL | G72: CANT. | H72: V.UNI | I72: V.TOTAL | J72: CANT. | K72: V.UNI | L72: V.TOTAL
B73: ='LIBRO DIARIO'!B7 -> 46027 | C73: SITUACIÓN INICIA DE LA INDUSTRIA | D73: 300000 | E73: =3/3000 -> 0.001 | F73: =D73*E73 -> 300 | J73: =D73-G73 -> 300000 | K73: =L73/J73 -> 0.001 | L73: =F73-I73 -> 300
B74: 46027 | C74: COMPRA SEGÙN FACTURA PARA OP#100 | D74: 0 | E74: 0 | F74: =D74*E74 -> 0 | J74: =J73+D74-G74 -> 300000 | K74: =L74/J74 -> 0.001 | L74: =L73+F74-I74 -> 300
B75: 46027 | C75: ENVIO A PRODUCCIÓN OP#100 TS | G75: =CÁLCULOS!E42 -> 16000 | H75: =K74 -> 0.001 | I75: =G75*H75 -> 16 | J75: =J74+D75-G75 -> 284000 | K75: =L75/J75 -> 0.001 | L75: =L74+F75-I75 -> 284
B76: 46027 | C76: ENVIO A PRODUCCIÓN OP#100 TM | G76: =CÁLCULOS!E43 -> 30000 | H76: =K75 -> 0.001 | I76: =G76*H76 -> 30 | J76: =J75+D76-G76 -> 254000 | K76: =L76/J76 -> 0.001 | L76: =L75+F76-I76 -> 254
B77: 46027 | C77: ENVIO A PRODUCCIÓN OP#100 TL | G77: =CÁLCULOS!E44 -> 30000 | H77: =K76 -> 0.001 | I77: =G77*H77 -> 30 | J77: =J76+D77-G77 -> 224000 | K77: =L77/J77 -> 0.001 | L77: =L76+F77-I77 -> 224
B78: ='LIBRO DIARIO'!B156 -> 0 | C78: COMPRA SEGÙN FACTURA PARA OP#101 | D78: =CÁLCULOS!E144 -> 0 | E78: =E74*1.1 -> 0 | F78: =D78*E78 -> 0 | J78: =J77+D78-G78 -> 224000 | K78: =L78/J78 -> 0.001 | L78: =L77+F78-I78 -> 224
B79: ='LIBRO DIARIO'!B98 -> 46037 | C79: ENVIO A PRODUCCIÓN OP#100 TS | G79: =CÁLCULOS!E119 -> 20000 | H79: =K78 -> 0.001 | I79: =G79*H79 -> 20 | J79: =J78+D79-G79 -> 204000 | K79: =L79/J79 -> 0.001 | L79: =L78+F79-I79 -> 204
B80: ='LIBRO DIARIO'!B98 -> 46037 | C80: ENVIO A PRODUCCIÓN OP#100 TM | G80: =CÁLCULOS!E120 -> 30000 | H80: =K79 -> 0.001 | I80: =G80*H80 -> 30 | J80: =J79+D80-G80 -> 174000 | K80: =L80/J80 -> 0.001 | L80: =L79+F80-I80 -> 174
B81: ='LIBRO DIARIO'!B98 -> 46037 | C81: ENVIO A PRODUCCIÓN OP#100 TL | G81: =CÁLCULOS!E121 -> 54000 | H81: =K80 -> 0.001 | I81: =G81*H81 -> 54 | J81: =J80+D81-G81 -> 120000 | K81: =L81/J81 -> 0.001 | L81: =L80+F81-I81 -> 120
B84: PRODUCTO: | C84: ='LIBRO DIARIO'!C81 -> PRODUCTO TERMINADO OP#100 TS
B85: UNIDAD MEDIA: UNITARIO | F85: MÉTODO: | H85: PROMEDIO | K85: No. | L85: 6
D86: ENTRADAS | G86: SALIDAS | J86: SALDOS
B87: FECHA | C87: DETALLE | D87: CANT. | E87: V.UNI | F87: V.TOTAL | G87: CANT. | H87: V.UNI | I87: V.TOTAL | J87: CANT. | K87: V.UNI | L87: V.TOTAL
B88: ='LIBRO DIARIO'!B80 -> 46036 | C88: ENTREGA DE PRODUCCIÓN OP#100 | D88: ='ORDEN P'!B10 -> 4000 | E88: =F88/D88 -> 5.3746738 | F88: ='LIBRO DIARIO'!F81 -> 21498.695 | J88: =D88-G88 -> 4000 | K88: =L88/J88 -> 5.3746738 | L88: =F88-I88 -> 21498.695
B89: ='LIBRO DIARIO'!B92 -> 46036 | C89: VENTA SEGUN FACTURA | G89: ='ORDEN P'!B10 -> 4000 | H89: =K88 -> 5.3746738 | I89: =G89*H89 -> 21498.695 | J89: =J88+D89-G89 -> 0 | K89: =L89/J89 -> #DIV/0! | L89: =L88+F89-I89 -> 0
J90: =J89+D90-G90 -> 0 | K90: =L90/J90 -> #DIV/0! | L90: =L89+F90-I90 -> 0
J91: =J90+D91-G91 -> 0 | K91: =L91/J91 -> #DIV/0! | L91: =L90+F91-I91 -> 0
J92: =J91+D92-G92 -> 0 | K92: =L92/J92 -> #DIV/0! | L92: =L91+F92-I92 -> 0
B98: PRODUCTO: BOTON | C98: ='LIBRO DIARIO'!C82 -> PRODUCTO TERMINADO OP#100 TM
B99: UNIDAD MEDIA: UNITARIO | F99: MÉTODO: | H99: PROMEDIO | K99: No. | L99: 7
D100: ENTRADAS | G100: SALIDAS | J100: SALDOS
B101: FECHA | C101: DETALLE | D101: CANT. | E101: V.UNI | F101: V.TOTAL | G101: CANT. | H101: V.UNI | I101: V.TOTAL | J101: CANT. | K101: V.UNI | L101: V.TOTAL
B102: ='LIBRO DIARIO'!B80 -> 46036 | C102: ENTREGA DE PRODUCCIÓN OP#100 | D102: ='ORDEN P'!B11 -> 6000 | E102: =F102/D102 -> 5.8693015 | F102: ='LIBRO DIARIO'!F82 -> 35215.809 | J102: =D102-G102 -> 6000 | K102: =L102/J102 -> 5.8693015 | L102: =F102-I102 -> 35215.809
B103: ='LIBRO DIARIO'!B92 -> 46036 | C103: VENTA SEGUN FACTURA | G103: ='ORDEN P'!B11 -> 6000 | H103: =K102 -> 5.8693015 | I103: =G103*H103 -> 35215.809 | J103: =J102+D103-G103 -> 0 | K103: =L103/J103 -> #DIV/0! | L103: =L102+F103-I103 -> 0
J104: =J103+D104-G104 -> 0 | K104: =L104/J104 -> #DIV/0! | L104: =L103+F104-I104 -> 0
J105: =J104+D105-G105 -> 0 | K105: =L105/J105 -> #DIV/0! | L105: =L104+F105-I105 -> 0
J106: =J105+D106-G106 -> 0 | K106: =L106/J106 -> #DIV/0! | L106: =L105+F106-I106 -> 0
B112: PRODUCTO: BOTON | C112: ='LIBRO DIARIO'!C83 -> PRODUCTO TERMINADO OP#100 TL
B113: UNIDAD MEDIA: UNITARIO | F113: MÉTODO: | H113: PROMEDIO | K113: No. | L113: 8
D114: ENTRADAS | G114: SALIDAS | J114: SALDOS
B115: FECHA | C115: DETALLE | D115: CANT. | E115: V.UNI | F115: V.TOTAL | G115: CANT. | H115: V.UNI | I115: V.TOTAL | J115: CANT. | K115: V.UNI | L115: V.TOTAL
B116: ='LIBRO DIARIO'!B80 -> 46036 | C116: ENTREGA DE PRODUCCIÓN OP#100 | D116: ='ORDEN P'!B12 -> 5000 | E116: =F116/D116 -> 6.8081004 | F116: ='LIBRO DIARIO'!F83 -> 34040.502 | J116: =D116-G116 -> 5000 | K116: =L116/J116 -> 6.8081004 | L116: =F116-I116 -> 34040.502
C117: VENTA SEGUN FACTURA | G117: ='ORDEN P'!B12 -> 5000 | H117: =K116 -> 6.8081004 | I117: =G117*H117 -> 34040.502 | J117: 0 | K117: =#DIV/0! -> #DIV/0! | L117: $ -
J118: =J117+D118-G118 -> 0 | K118: =L118/J118 -> #VALUE! | L118: =L117+F118-I118 -> #VALUE!
J119: =J118+D119-G119 -> 0 | K119: =L119/J119 -> #VALUE! | L119: =L118+F119-I119 -> #VALUE!
J120: =J119+D120-G120 -> 0 | K120: =L120/J120 -> #VALUE! | L120: =L119+F120-I120 -> #VALUE!

Sheet CÁLCULOS
B2: MATERIA PRIMA DIRECTA
B3: TELA
B4: PRODUCTOS | C4: CANTIDAD | D4: REQUERIMIENTO | E4: TOTAL | G4: INVENTARIO | H4: COMPRA | I4: INV. FINAL | J4: COMPRA OPTIMA
B5: CAMISETA S | C5: ='ORDEN P'!B10 -> 4000 | D5: 80 | E5: =C5*D5 -> 320000 | F5: =E5/100 -> 3200
B6: CAMISETA L | C6: ='ORDEN P'!B11 -> 6000 | D6: 90 | E6: =C6*D6 -> 540000 | F6: =E6/100 -> 5400
B7: CAMISETA M | C7: ='ORDEN P'!B12 -> 5000 | D7: 110 | E7: =C7*D7 -> 550000 | F7: =E7/100 -> 5500
D8: CENTÍMETROS: | E8: =SUM(E5:E7) -> 1410000 | F8: =E8/100 -> 14100
D9: METRO: | E9: =E8/100 -> 14100 | G9: =KARDEX!J9 -> 4500 | H9: =E9-G9 -> 9600 | I9: =DATOS!F25 -> 5616 | J9: =H9+I9 -> 15216
B12: MATERIA PRIMA DIRECTA
B13: CUELLOS
B14: PRODUCTOS | C14: CANTIDAD | D14: REQUERIMIENTO | E14: TOTAL | G14: INVENTARIO | H14: COMPRA | I14: INV. FINAL | J14: COMPRA OPTIMA
B15: CAMISETA S | C15: ='ORDEN P'!B10 -> 4000 | D15: 1 | E15: =C15*D15 -> 4000
B16: CAMISETA L | C16: ='ORDEN P'!B11 -> 6000 | D16: 1 | E16: =C16*D16 -> 6000
B17: CAMISETA M | C17: ='ORDEN P'!B12 -> 5000 | D17: 1 | E17: =C17*D17 -> 5000
D18: UNIDADES: | E18: =SUM(E15:E17) -> 15000 | G18: =KARDEX!J25 -> 3000 | H18: =E18-G18 -> 12000 | I18: 6000 | J18: =H18+I18 -> 18000
B21: MATERIA PRIMA DIRECTA
B22: PUÑOS
B23: PRODUCTOS | C23: CANTIDAD | D23: REQUERIMIENTO | E23: TOTAL | G23: INVENTARIO | H23: COMPRA | I23: INV. FINAL | J23: COMPRA OPTIMA
B24: CAMISETA S | C24: ='ORDEN P'!B10 -> 4000 | D24: 2 | E24: =C24*D24 -> 8000
B25: CAMISETA L | C25: ='ORDEN P'!B11 -> 6000 | D25: 2 | E25: =C25*D25 -> 12000
B26: CAMISETA M | C26: ='ORDEN P'!B12 -> 5000 | D26: 2 | E26: =C26*D26 -> 10000
D27: UNIDADES: | E27: =SUM(E24:E26) -> 30000 | G27: =KARDEX!J41 -> 5000 | H27: =E27-G27 -> 25000 | I27: 12000 | J27: =H27+I27 -> 37000
B30: MATERIA PRIMA DIRECTA
B31: BOTÓN
B32: PRODUCTOS | C32: CANTIDAD | D32: REQUERIMIENTO | E32: TOTAL | G32: INVENTARIO | H32: COMPRA | I32: INV. FINAL | J32: COMPRA OPTIMA
B33: CAMISETA S | C33: ='ORDEN P'!B10 -> 4000 | D33: 2 | E33: =C33*D33 -> 8000
B34: CAMISETA L | C34: ='ORDEN P'!B11 -> 6000 | D34: 2 | E34: =C34*D34 -> 12000
B35: CAMISETA M | C35: ='ORDEN P'!B12 -> 5000 | D35: 2 | E35: =C35*D35 -> 10000
D36: UNIDADES: | E36: =SUM(E33:E35) -> 30000 | G36: =KARDEX!J57 -> 40000 | H36: =E36-G36 -> -10000 | I36: 12000 | J36: =H36+I36 -> 2000
B39: MATERIA PRIMA DIRECTA
B40: HILO
B41: PRODUCTOS | C41: CANTIDAD | D41: REQUERIMIENTO | E41: TOTAL | G41: INVENTARIO | H41: COMPRA | I41: INV. FINAL | J41: COMPRA OPTIMA
B42: CAMISETA S | C42: ='ORDEN P'!B10 -> 4000 | D42: 4 | E42: =C42*D42 -> 16000
B43: CAMISETA L | C43: ='ORDEN P'!B11 -> 6000 | D43: 5 | E43: =C43*D43 -> 30000
B44: CAMISETA M | C44: ='ORDEN P'!B12 -> 5000 | D44: 6 | E44: =C44*D44 -> 30000
D45: METROS: | E45: =SUM(E42:E44) -> 76000 | G45: =KARDEX!J73 -> 300000 | H45: =E45-G45 -> -224000 | I45: 90000 | J45: =H45+I45 -> -134000
B47: MANO DE OBRA DIRECTA ene 2026
B49: L | C49: M | D49: M | E49: J | F49: V
B50: 5 | C50: 6 | D50: 7 | E50: 8 | F50: 9 | G50: OP #100
B51: 12 | C51: 13 | D51: 14 | E51: 15 | F51: 16
B52: 19 | C52: 20 | D52: 21 | E52: 22 | F52: 23
B53: 26 | C53: 27 | D53: 28 | E53: 29 | F53: 30
B56: 3 COSTOS INDIRECTOS DE FABRICACIÓN
B57: CIF
B59: MATERIA PRIMA INDIRECTA
B60: MANO DE OBRA INDIRECTA
E62: DISTRIBUCIÓN | G62: ='ORDEN P'!C10 -> CAMISETA S | H62: ='ORDEN P'!C11 -> CAMISETA M | I62: ='ORDEN P'!C12 -> CAMISETA L
B63: CIF | D63: VALOR ANNUAL | E63: UNIDADES PRODUCIDAS | F63: COSTO POR UNIDAD | G63: ='ORDEN P'!B10 -> 4000 | H63: ='ORDEN P'!B11 -> 6000 | I63: ='ORDEN P'!B12 -> 5000 | J63: TOTAL
B64: ENERGÍA ELÉCTRICA | D64: =500*12 -> 6000 | E64: 480000 | F64: =D64/$E$64 -> 0.0125 | G64: =$G$63*F64 -> 50 | H64: =$H$63*F64 -> 75 | I64: =$I$63*F64 -> 62.5 | J64: =SUM(G64:I64) -> 187.5
B65: MANTENIMIENTO | D65: =(25*30)*12 -> 9000 | F65: =D65/$E$64 -> 0.01875 | G65: =$G$63*F65 -> 75 | H65: =$H$63*F65 -> 112.5 | I65: =$I$63*F65 -> 93.75 | J65: =SUM(G65:I65) -> 281.25
B66: SEGUROS DE FÁBRICA | D66: =350*12 -> 4200 | F66: =D66/$E$64 -> 0.00875 | G66: =$G$63*F66 -> 35 | H66: =$H$63*F66 -> 52.5 | I66: =$I$63*F66 -> 43.75 | J66: =SUM(G66:I66) -> 131.25
B67: DEPRECIACIÓN MAQUINARIA | D67: ='LIBRO DIARIO'!F11*10% -> 7000 | F67: =D67/$E$64 -> 0.014583333 | G67: =$G$63*F67 -> 58.333333 | H67: =$H$63*F67 -> 87.5 | I67: =$I$63*F67 -> 72.916667 | J67: =SUM(G67:I67) -> 218.75
G68: =SUM(G64:G67) -> 218.33333 | H68: =SUM(H64:H67) -> 327.5 | I68: =SUM(I64:I67) -> 272.91667 | J68: =SUM(G68:I68) -> 818.75
B71: VENTAS | C71: CANTIDAD | D71: PVP | E71: TOTAL
B72: ='ORDEN P'!C10 -> CAMISETA S | C72: ='ORDEN P'!B10 -> 4000 | D72: =KARDEX!K88*1.8 -> 9.6744128 | E72: =C72*D72 -> 38697.651
B73: ='ORDEN P'!C11 -> CAMISETA M | C73: ='ORDEN P'!B11 -> 6000 | D73: =KARDEX!K102*1.8 -> 10.564743 | E73: =C73*D73 -> 63388.456
B74: ='ORDEN P'!C12 -> CAMISETA L | C74: ='ORDEN P'!B12 -> 5000 | D74: =KARDEX!K116*1.8 -> 12.254581 | E74: =C74*D74 -> 61272.903
E75: =SUM(E72:E74) -> 163359.01
B79: MATERIA PRIMA DIRECTA
B80: TELA
B81: PRODUCTOS | C81: CANTIDAD | D81: REQUERIMIENTO | E81: TOTAL | G81: INVENTARIO | H81: COMPRA | I81: INV. FINAL | J81: COMPRA OPTIMA
B82: CAMISETA S | C82: =DATOS!C52 -> 5000 | D82: 80 | E82: =C82*D82 -> 400000 | F82: =E82/100 -> 4000
B83: CAMISETA M | C83: =DATOS!C53 -> 6000 | D83: 90 | E83: =C83*D83 -> 540000 | F83: =E83/100 -> 5400
B84: CAMISETA L | C84: =DATOS!C54 -> 9000 | D84: 110 | E84: =C84*D84 -> 990000 | F84: =E84/100 -> 9900
D85: CENTÍMETROS: | E85: =SUM(E82:E84) -> 1930000 | F85: =E85/100 -> 19300
D86: METRO: | E86: =E85/100 -> 19300 | G86: =KARDEX!J13 -> 5616 | H86: =E86-G86 -> 13684 | I86: =DATOS!F25 -> 5616 | J86: =H86+I86 -> 19300
B89: MATERIA PRIMA DIRECTA
B90: CUELLOS
B91: PRODUCTOS | C91: CANTIDAD | D91: REQUERIMIENTO | E91: TOTAL | G91: INVENTARIO | H91: COMPRA | I91: INV. FINAL | J91: COMPRA OPTIMA
B92: CAMISETA S | C92: =C82 -> 5000 | D92: 1 | E92: =C92*D92 -> 5000
B93: CAMISETA M | C93: =C83 -> 6000 | D93: 1 | E93: =C93*D93 -> 6000
B94: CAMISETA L | C94: =C84 -> 9000 | D94: 1 | E94: =C94*D94 -> 9000
D95: UNIDADES: | E95: =SUM(E92:E94) -> 20000 | G95: =KARDEX!J29 -> 6000 | H95: =E95-G95 -> 14000 | I95: 6000 | J95: =H95+I95 -> 20000
B98: MATERIA PRIMA DIRECTA
B99: PUÑOS
B100: PRODUCTOS | C100: CANTIDAD | D100: REQUERIMIENTO | E100: TOTAL | G100: INVENTARIO | H100: COMPRA | I100: INV. FINAL | J100: COMPRA OPTIMA
B101: CAMISETA S | C101: 5000 | D101: 2 | E101: =C101*D101 -> 10000
B102: CAMISETA M | C102: 6000 | D102: 2 | E102: =C102*D102 -> 12000
B103: CAMISETA L | C103: 9000 | D103: 2 | E103: =C103*D103 -> 18000
D104: UNIDADES: | E104: =SUM(E101:E103) -> 40000 | G104: =KARDEX!J45 -> 12000 | H104: =E104-G104 -> 28000 | I104: 12000 | J104: =H104+I104 -> 40000
B107: MATERIA PRIMA DIRECTA
B108: BOTÓN
B109: PRODUCTOS | C109: CANTIDAD | D109: REQUERIMIENTO | E109: TOTAL | G109: INVENTARIO | H109: COMPRA | I109: INV. FINAL | J109: COMPRA OPTIMA
B110: CAMISETA S | C110: 5000 | D110: 2 | E110: =C110*D110 -> 10000
B111: CAMISETA M | C111: 6000 | D111: 2 | E111: =C111*D111 -> 12000
B112: CAMISETA L | C112: 9000 | D112: 2 | E112: =C112*D112 -> 18000
D113: UNIDADES: | E113: =SUM(E110:E112) -> 40000 | G113: =KARDEX!J61 -> 12000 | H113: =E113-G113 -> 28000 | I113: 12000 | J113: =H113+I113 -> 40000
B116: MATERIA PRIMA DIRECTA
B117: HILO
B118: PRODUCTOS | C118: CANTIDAD | D118: REQUERIMIENTO | E118: TOTAL | G118: INVENTARIO | H118: COMPRA | I118: INV. FINAL | J118: COMPRA OPTIMA
B119: CAMISETA S | C119: 5000 | D119: 4 | E119: =C119*D119 -> 20000
B120: CAMISETA M | C120: 6000 | D120: 5 | E120: =C120*D120 -> 30000
B121: CAMISETA L | C121: 9000 | D121: 6 | E121: =C121*D121 -> 54000
D122: METROS: | E122: =SUM(E119:E121) -> 104000 | G122: =KARDEX!J77 -> 224000 | H122: =E122-G122 -> -120000 | I122: 90000 | J122: =H122+I122 -> -30000
B124: MANO DE OBRA DIRECTA ene 2026
B126: L | C126: M | D126: M | E126: J | F126: V
B127: 5 | C127: 6 | D127: 7 | E127: 8 | F127: 9 | G127: OP #100
B128: 12 | C128: 13 | D128: 14 | E128: 15 | F128: 16 | G128: OP #101
B129: 19 | C129: 20 | D129: 21 | E129: 22 | F129: 23
B130: 26 | C130: 27 | D130: 28 | E130: 29 | F130: 30
...

Sheet ORDEN P
B2: INDUSTRIAS "ALAN SPORT" | F2: INDUSTRIAS "ALAN SPORT"
B3: ORDEN DE PRODUCCIÓN | F3: ORDEN DE PRODUCCIÓN
B4: NÚMERO: | C4: 100 | F4: NÚMERO: | G4: 101
B5: CLIENTE | C5: TOMY | F5: CLIENTE | G5: TEXPAX
B6: FECHA DE INICIO | C6: 46027 | F6: FECHA DE INICIO | G6: 46037
B7: FECHA DE TERMINACIÓN: | F7: FECHA DE TERMINACIÓN:
B9: CANTIDAD | C9: PRODUCTO | D9: OBSERVACIÓN | F9: CANTIDAD | G9: PRODUCTO | H9: OBSERVACIÓN
B10: 4000 | C10: CAMISETA S | D10: CON BORDADO | F10: =DATOS!C52 -> 5000 | G10: CAMISETA S | H10: CON BORDADO
B11: 6000 | C11: CAMISETA M | D11: CON BORDADO | F11: =DATOS!C53 -> 6000 | G11: CAMISETA M | H11: CON BORDADO
B12: 5000 | C12: CAMISETA L | D12: CON BORDADO | F12: =DATOS!C54 -> 9000 | G12: CAMISETA L | H12: CON BORDADO
B13: =SUM(B10:B12) -> 15000 | F13: =SUM(F10:F12) -> 20000
B15: ….......................................... | D15: …............................... | F15: ….......................................... | H15: …...............................
B16: CLIENTE | D16: JEFE DE VENTAS | F16: CLIENTE | H16: JEFE DE VENTAS

Sheet ROL MOD
A2: ROL DE PAGOS
B3: MANO DE OBRA DIRECTA | H3: HORAS EXTRAS Y SUPLEMENTARIAS
A4: No. | B4: NOMBRES Y APELLIDOS | C4: CARGO | D4: FECHA INGRESO | E4: SUELDO | F4: DIAS TRABAJADOS | G4: SUELDO LIQUIDO | H4: 0.25 | I4: 0.5 | J4: 1 | K4: OTROS INGRESOS | L4: FONDO DE RESERVA | M4: TOTAL DE INGRESOS | N4: APORTE PERSONAL iess | O4: IMPUESTO RENTA | P4: RETENCIONES JUDICIALES | Q4: 0TROS DESCUENTOS | R4: TOTAL EGRESOS | S4: VALOR A RECIBIR
A5: 1 | B5: Alan Brito Delgado | C5: Obreros | D5: 45658 | E5: 482 | F5: 30 | G5: =(E5/30)*F5 -> 482 | H5: =((E5/160)*1.25)*0 -> 0 | I5: =((E5/160)*1.5)*4 -> 18.075 | J5: =((E5/160)*2)*8 -> 48.2 | L5: =(G5+H5+I5+J5+K5)/12 -> 45.689583 | M5: =+G5+H5+I5+J5+K5+L5 -> 593.96458 | N5: =(M5-L5)*9.45% -> 51.811988 | P5: 0 | R5: =+N5+O5+P5+Q5 -> 51.811988 | S5: =M5-R5 -> 542.1526
A6: 2 | B6: Nori Navas Robles | C6: Obreros | D6: 45659 | E6: 482 | F6: 30 | G6: =(E6/30)*F6 -> 482 | H6: =((E6/160)*1.25)*0 -> 0 | I6: =((E6/160)*1.5)*4 -> 18.075 | J6: =((E6/160)*2)*8 -> 48.2 | L6: =(G6+H6+I6+J6+K6)/12 -> 45.689583 | M6: =+G6+H6+I6+J6+K6+L6 -> 593.96458 | N6: =(M6-L6)*9.45% -> 51.811988 | P6: 0 | R6: =+N6+O6+P6+Q6 -> 51.811988 | S6: =M6-R6 -> 542.1526
A7: 3 | B7: Zoila Vaca Martinez | C7: Obreros | D7: 45660 | E7: 482 | F7: 30 | G7: =(E7/30)*F7 -> 482 | H7: =((E7/160)*1.25)*0 -> 0 | I7: =((E7/160)*1.5)*4 -> 18.075 | J7: =((E7/160)*2)*8 -> 48.2 | L7: =(G7+H7+I7+J7+K7)/12 -> 45.689583 | M7: =+G7+H7+I7+J7+K7+L7 -> 593.96458 | N7: =(M7-L7)*9.45% -> 51.811988 | P7: 0 | R7: =+N7+O7+P7+Q7 -> 51.811988 | S7: =M7-R7 -> 542.1526
A8: 4 | B8: Giuliana Armas | C8: Obreros | D8: 45661 | E8: 482 | F8: 30 | G8: =(E8/30)*F8 -> 482 | H8: =((E8/160)*1.25)*0 -> 0 | I8: =((E8/160)*1.5)*4 -> 18.075 | J8: =((E8/160)*2)*8 -> 48.2 | L8: =(G8+H8+I8+J8+K8)/12 -> 45.689583 | M8: =+G8+H8+I8+J8+K8+L8 -> 593.96458 | N8: =(M8-L8)*9.45% -> 51.811988 | P8: 0 | R8: =+N8+O8+P8+Q8 -> 51.811988 | S8: =M8-R8 -> 542.1526
A9: 5 | B9: Valeria Cortez | C9: Obreros | D9: 45662 | E9: 482 | F9: 30 | G9: =(E9/30)*F9 -> 482 | H9: =((E9/160)*1.25)*0 -> 0 | I9: =((E9/160)*1.5)*4 -> 18.075 | J9: =((E9/160)*2)*8 -> 48.2 | L9: =(G9+H9+I9+J9+K9)/12 -> 45.689583 | M9: =+G9+H9+I9+J9+K9+L9 -> 593.96458 | N9: =(M9-L9)*9.45% -> 51.811988 | P9: 0 | R9: =+N9+O9+P9+Q9 -> 51.811988 | S9: =M9-R9 -> 542.1526
A10: 6 | B10: Giuliana Armas | C10: Obreros | D10: 45663 | E10: 482 | F10: 30 | G10: =(E10/30)*F10 -> 482 | H10: =((E10/160)*1.25)*0 -> 0 | I10: =((E10/160)*1.5)*4 -> 18.075 | J10: =((E10/160)*2)*8 -> 48.2 | L10: =(G10+H10+I10+J10+K10)/12 -> 45.689583 | M10: =+G10+H10+I10+J10+K10+L10 -> 593.96458 | N10: =(M10-L10)*9.45% -> 51.811988 | P10: 0 | R10: =+N10+O10+P10+Q10 -> 51.811988 | S10: =M10-R10 -> 542.1526
A11: 7 | B11: Valeria Cortez | C11: Obreros | D11: 45664 | E11: 482 | F11: 30 | G11: =(E11/30)*F11 -> 482 | H11: =((E11/160)*1.25)*0 -> 0 | I11: =((E11/160)*1.5)*4 -> 18.075 | J11: =((E11/160)*2)*8 -> 48.2 | L11: =(G11+H11+I11+J11+K11)/12 -> 45.689583 | M11: =+G11+H11+I11+J11+K11+L11 -> 593.96458 | N11: =(M11-L11)*9.45% -> 51.811988 | P11: 0 | R11: =+N11+O11+P11+Q11 -> 51.811988 | S11: =M11-R11 -> 542.1526
A12: 8 | B12: Giuliana Armas | C12: Obreros | D12: 45665 | E12: 482 | F12: 30 | G12: =(E12/30)*F12 -> 482 | H12: =((E12/160)*1.25)*0 -> 0 | I12: =((E12/160)*1.5)*4 -> 18.075 | J12: =((E12/160)*2)*8 -> 48.2 | L12: =(G12+H12+I12+J12+K12)/12 -> 45.689583 | M12: =+G12+H12+I12+J12+K12+L12 -> 593.96458 | N12: =(M12-L12)*9.45% -> 51.811988 | P12: 0 | R12: =+N12+O12+P12+Q12 -> 51.811988 | S12: =M12-R12 -> 542.1526
A13: 9 | B13: Valeria Cortez | C13: Obreros | D13: 45666 | E13: 482 | F13: 30 | G13: =(E13/30)*F13 -> 482 | H13: =((E13/160)*1.25)*0 -> 0 | I13: =((E13/160)*1.5)*4 -> 18.075 | J13: =((E13/160)*2)*8 -> 48.2 | L13: =(G13+H13+I13+J13+K13)/12 -> 45.689583 | M13: =+G13+H13+I13+J13+K13+L13 -> 593.96458 | N13: =(M13-L13)*9.45% -> 51.811988 | P13: 0 | R13: =+N13+O13+P13+Q13 -> 51.811988 | S13: =M13-R13 -> 542.1526
A14: 10 | B14: Giuliana Armas | C14: Obreros | D14: 45667 | E14: 482 | F14: 30 | G14: =(E14/30)*F14 -> 482 | H14: =((E14/160)*1.25)*0 -> 0 | I14: =((E14/160)*1.5)*4 -> 18.075 | J14: =((E14/160)*2)*8 -> 48.2 | L14: =(G14+H14+I14+J14+K14)/12 -> 45.689583 | M14: =+G14+H14+I14+J14+K14+L14 -> 593.96458 | N14: =(M14-L14)*9.45% -> 51.811988 | P14: 0 | R14: =+N14+O14+P14+Q14 -> 51.811988 | S14: =M14-R14 -> 542.1526
A15: 11 | B15: Valeria Cortez | C15: Obreros | D15: 45668 | E15: 482 | F15: 30 | G15: =(E15/30)*F15 -> 482 | H15: =((E15/160)*1.25)*0 -> 0 | I15: =((E15/160)*1.5)*4 -> 18.075 | J15: =((E15/160)*2)*8 -> 48.2 | L15: =(G15+H15+I15+J15+K15)/12 -> 45.689583 | M15: =+G15+H15+I15+J15+K15+L15 -> 593.96458 | N15: =(M15-L15)*9.45% -> 51.811988 | P15: 0 | R15: =+N15+O15+P15+Q15 -> 51.811988 | S15: =M15-R15 -> 542.1526
A16: 12 | B16: Giuliana Armas | C16: Obreros | D16: 45669 | E16: 482 | F16: 30 | G16: =(E16/30)*F16 -> 482 | H16: =((E16/160)*1.25)*0 -> 0 | I16: =((E16/160)*1.5)*4 -> 18.075 | J16: =((E16/160)*2)*8 -> 48.2 | L16: =(G16+H16+I16+J16+K16)/12 -> 45.689583 | M16: =+G16+H16+I16+J16+K16+L16 -> 593.96458 | N16: =(M16-L16)*9.45% -> 51.811988 | P16: 0 | R16: =+N16+O16+P16+Q16 -> 51.811988 | S16: =M16-R16 -> 542.1526
... A19: 15 | B19: Valeria Cortez | C19: Obreros | D19: 45672 | E19: 482 | F19: 30 | G19: =(E19/30)*F19 -> 482 | H19: =((E19/160)*1.25)*0 -> 0 | I19: =((E19/160)*1.5)*4 -> 18.075 | J19: =((E19/160)*2)*8 -> 48.2 | L19: =(G19+H19+I19+J19+K19)/12 -> 45.689583 | M19: =+G19+H19+I19+J19+K19+L19 -> 593.96458 | N19: =(M19-L19)*9.45% -> 51.811988 | P19: 0 | R19: =+N19+O19+P19+Q19 -> 51.811988 | S19: =M19-R19 -> 542.1526
A20: 16 | B20: Giuliana Armas | C20: Obreros | D20: 45673 | E20: 482 | F20: 30 | G20: =(E20/30)*F20 -> 482 | H20: =((E20/160)*1.25)*0 -> 0 | I20: =((E20/160)*1.5)*4 -> 18.075 | J20: =((E20/160)*2)*8 -> 48.2 | L20: =(G20+H20+I20+J20+K20)/12*0 -> 0 | M20: =+G20+H20+I20+J20+K20+L20 -> 548.275 | N20: =(M20-L20)*9.45% -> 51.811988 | P20: 0 | R20: =+N20+O20+P20+Q20 -> 51.811988 | S20: =M20-R20 -> 496.46301
A21: 17 | B21: Valeria Cortez | C21: Obreros | D21: 45674 | E21: 482 | F21: 30 | G21: =(E21/30)*F21 -> 482 | H21: =((E21/160)*1.25)*0 -> 0 | I21: =((E21/160)*1.5)*4 -> 18.075 | J21: =((E21/160)*2)*8 -> 48.2 | L21: =(G21+H21+I21+J21+K21)/12*0 -> 0 | M21: =+G21+H21+I21+J21+K21+L21 -> 548.275 | N21: =(M21-L21)*9.45% -> 51.811988 | P21: 0 | R21: =+N21+O21+P21+Q21 -> 51.811988 | S21: =M21-R21 -> 496.46301
A22: 18 | B22: Giuliana Armas | C22: Obreros | D22: 45675 | E22: 482 | F22: 30 | G22: =(E22/30)*F22 -> 482 | H22: =((E22/160)*1.25)*0 -> 0 | I22: =((E22/160)*1.5)*4 -> 18.075 | J22: =((E22/160)*2)*8 -> 48.2 | L22: =(G22+H22+I22+J22+K22)/12*0 -> 0 | M22: =+G22+H22+I22+J22+K22+L22 -> 548.275 | N22: =(M22-L22)*9.45% -> 51.811988 | P22: 0 | R22: =+N22+O22+P22+Q22 -> 51.811988 | S22: =M22-R22 -> 496.46301
A23: 19 | B23: Valeria Cortez | C23: Obreros | D23: 45676 | E23: 482 | F23: 30 | G23: =(E23/30)*F23 -> 482 | H23: =((E23/160)*1.25)*0 -> 0 | I23: =((E23/160)*1.5)*4 -> 18.075 | J23: =((E23/160)*2)*8 -> 48.2 | L23: =(G23+H23+I23+J23+K23)/12*0 -> 0 | M23: =+G23+H23+I23+J23+K23+L23 -> 548.275 | N23: =(M23-L23)*9.45% -> 51.811988 | P23: 0 | R23: =+N23+O23+P23+Q23 -> 51.811988 | S23: =M23-R23 -> 496.46301
A24: 20 | B24: Giuliana Armas | C24: Obreros | D24: 45677 | E24: 482 | F24: 30 | G24: =(E24/30)*F24 -> 482 | H24: =((E24/160)*1.25)*0 -> 0 | I24: =((E24/160)*1.5)*4 -> 18.075 | J24: =((E24/160)*2)*8 -> 48.2 | L24: =(G24+H24+I24+J24+K24)/12*0 -> 0 | M24: =+G24+H24+I24+J24+K24+L24 -> 548.275 | N24: =(M24-L24)*9.45% -> 51.811988 | P24: 0 | R24: =+N24+O24+P24+Q24 -> 51.811988 | S24: =M24-R24 -> 496.46301
A25: 21 | B25: Valeria Cortez | C25: Obreros | D25: 45678 | E25: 482 | F25: 30 | G25: =(E25/30)*F25 -> 482 | H25: =((E25/160)*1.25)*0 -> 0 | I25: =((E25/160)*1.5)*4 -> 18.075 | J25: =((E25/160)*2)*8 -> 48.2 | L25: =(G25+H25+I25+J25+K25)/12*0 -> 0 | M25: =+G25+H25+I25+J25+K25+L25 -> 548.275 | N25: =(M25-L25)*9.45% -> 51.811988 | P25: 0 | R25: =+N25+O25+P25+Q25 -> 51.811988 | S25: =M25-R25 -> 496.46301
A26: 22 | B26: Giuliana Armas | C26: Obreros | D26: 45679 | E26: 482 | F26: 30 | G26: =(E26/30)*F26 -> 482 | H26: =((E26/160)*1.25)*0 -> 0 | I26: =((E26/160)*1.5)*4 -> 18.075 | J26: =((E26/160)*2)*8 -> 48.2 | L26: =(G26+H26+I26+J26+K26)/12*0 -> 0 | M26: =+G26+H26+I26+J26+K26+L26 -> 548.275 | N26: =(M26-L26)*9.45% -> 51.811988 | P26: 0 | R26: =+N26+O26+P26+Q26 -> 51.811988 | S26: =M26-R26 -> 496.46301
A27: 23 | B27: Valeria Cortez | C27: Obreros | D27: 45680 | E27: 482 | F27: 30 | G27: =(E27/30)*F27 -> 482 | H27: =((E27/160)*1.25)*0 -> 0 | I27: =((E27/160)*1.5)*4 -> 18.075 | J27: =((E27/160)*2)*8 -> 48.2 | L27: =(G27+H27+I27+J27+K27)/12*0 -> 0 | M27: =+G27+H27+I27+J27+K27+L27 -> 548.275 | N27: =(M27-L27)*9.45% -> 51.811988 | P27: 0 | R27: =+N27+O27+P27+Q27 -> 51.811988 | S27: =M27-R27 -> 496.46301
A28: 24 | B28: Giuliana Armas | C28: Obreros | D28: 45681 | E28: 482 | F28: 30 | G28: =(E28/30)*F28 -> 482 | H28: =((E28/160)*1.25)*0 -> 0 | I28: =((E28/160)*1.5)*4 -> 18.075 | J28: =((E28/160)*2)*8 -> 48.2 | L28: =(G28+H28+I28+J28+K28)/12*0 -> 0 | M28: =+G28+H28+I28+J28+K28+L28 -> 548.275 | N28: =(M28-L28)*9.45% -> 51.811988 | P28: 0 | R28: =+N28+O28+P28+Q28 -> 51.811988 | S28: =M28-R28 -> 496.46301
A29: 25 | B29: Valeria Cortez | C29: Obreros | D29: 45682 | E29: 482 | F29: 30 | G29: =(E29/30)*F29 -> 482 | H29: =((E29/160)*1.25)*0 -> 0 | I29: =((E29/160)*1.5)*4 -> 18.075 | J29: =((E29/160)*2)*8 -> 48.2 | L29: =(G29+H29+I29+J29+K29)/12*0 -> 0 | M29: =+G29+H29+I29+J29+K29+L29 -> 548.275 | N29: =(M29-L29)*9.45% -> 51.811988 | P29: 0 | R29: =+N29+O29+P29+Q29 -> 51.811988 | S29: =M29-R29 -> 496.46301
A30: 26 | B30: Giuliana Armas | C30: Obreros | D30: 45683 | E30: 482 | F30: 30 | G30: =(E30/30)*F30 -> 482 | H30: =((E30/160)*1.25)*0 -> 0 | I30: =((E30/160)*1.5)*4 -> 18.075 | J30: =((E30/160)*2)*8 -> 48.2 | L30: =(G30+H30+I30+J30+K30)/12*0 -> 0 | M30: =+G30+H30+I30+J30+K30+L30 -> 548.275 | N30: =(M30-L30)*9.45% -> 51.811988 | P30: 0 | R30: =+N30+O30+P30+Q30 -> 51.811988 | S30: =M30-R30 -> 496.46301
A31: 27 | B31: Valeria Cortez | C31: Obreros | D31: 45684 | E31: 482 | F31: 30 | G31: =(E31/30)*F31 -> 482 | H31: =((E31/160)*1.25)*0 -> 0 | I31: =((E31/160)*1.5)*4 -> 18.075 | J31: =((E31/160)*2)*8 -> 48.2 | L31: =(G31+H31+I31+J31+K31)/12*0 -> 0 | M31: =+G31+H31+I31+J31+K31+L31 -> 548.275 | N31: =(M31-L31)*9.45% -> 51.811988 | P31: 0 | R31: =+N31+O31+P31+Q31 -> 51.811988 | S31: =M31-R31 -> 496.46301
... A34: 30 | B34: Giuliana Armas | C34: Obreros | D34: 45687 | E34: 482 | F34: 30 | G34: =(E34/30)*F34 -> 482 | H34: =((E34/160)*1.25)*0 -> 0 | I34: =((E34/160)*1.5)*4 -> 18.075 | J34: =((E34/160)*2)*8 -> 48.2 | L34: =(G34+H34+I34+J34+K34)/12*0 -> 0 | M34: =+G34+H34+I34+J34+K34+L34 -> 548.275 | N34: =(M34-L34)*9.45% -> 51.811988 | P34: 0 | R34: =+N34+O34+P34+Q34 -> 51.811988 | S34: =M34-R34 -> 496.46301
E35: =SUM(E5:E34) -> 14460 | F35: =SUM(F5:F34) -> 900 | G35: =SUM(G5:G34) -> 14460 | H35: =SUM(H5:H34) -> 0 | I35: =SUM(I5:I34) -> 542.25 | J35: =SUM(J5:J34) -> 1446 | K35: =SUM(K5:K34) -> 0 | L35: =SUM(L5:L34) -> 685.34375 | ... S35: =SUM(S5:S34) -> 15579.234
B37: MANO DE OBRA INDIRECTA | H37: HORAS EXTRAS Y SUPLEMENTARIAS
A38: No. | B38: NOMBRES Y APELLIDOS | C38: CARGO | D38: FECHA INGRESO | E38: SUELDO | F38: DIAS TRABAJADOS | G38: SUELDO LIQUIDO | H38: 0.25 | I38: 0.5 | J38: 1 | K38: OTROS INGRESOS | L38: FONDO DE RESERVA | M38: TOTAL DE INGRESOS | N38: APORTE PERSONAL iess | O38: IMPUESTO RENTA | P38: RETENCIONES JUDICIALES | Q38: 0TROS DESCUENTOS | R38: TOTAL EGRESOS | S38: VALOR A RECIBIR
A39: 1 | B39: Alan Brito Delgado | C39: Jefe de Producción | D39: 45658 | E39: 700 | F39: 30 | G39: =(E39/30)*F39 -> 700 | H39: =((E39/160)*1.25)*0 -> 0 | I39: =((E39/160)*1.5)*4 -> 26.25 | J39: =((E39/160)*2)*8 -> 70 | K39: 100 | L39: =(G39+H39+I39+J39+K39)/12 -> 74.6875 | M39: =+G39+H39+I39+J39+K39+L39 -> 970.9375 | N39: =(M39-L39)*9.45% -> 84.695625 | P39: 0 | R39: =+N39+O39+P39+Q39 -> 84.695625 | S39: =M39-R39 -> 886.24188
A40: 2 | B40: Nori Navas Robles | C40: Supervisor | D40: 45659 | E40: 650 | F40: 30 | G40: =(E40/30)*F40 -> 650 | H40: =((E40/160)*1.25)*0 -> 0 | I40: =((E40/160)*1.5)*4 -> 24.375 | J40: =((E40/160)*2)*8 -> 65 | K40: 60 | L40: =(G40+H40+I40+J40+K40)/12 -> 66.614583 | M40: =+G40+H40+I40+J40+K40+L40 -> 865.98958 | N40: =(M40-L40)*9.45% -> 75.540937 | P40: 0 | R40: =+N40+O40+P40+Q40 -> 75.540937 | S40: =M40-R40 -> 790.44865
G41: =SUM(G39:G40) -> 1350 | H41: =SUM(H39:H40) -> 0 | I41: =SUM(I39:I40) -> 50.625 | J41: =SUM(J39:J40) -> 135 | K41: =SUM(K39:K40) -> 160 | L41: =SUM(L39:L40) -> 141.30208 | M41: =SUM(M39:M40) -> 1836.9271 | N41: =SUM(N39:N40) -> 160.23656 | ... S41: =SUM(S39:S40) -> 1676.6905
A42: ROL DE PROVISIONES
D43: Rol de proviciones
A46: No. | B46: NOMBRES Y APELLIDOS | C46: CARGO | D46: FECHA INGRESO | E46: TOTAL DE INGRESOS | F46: XIII SUELDO | G46: XIV SUELDO | H46: VACACIONES | I46: FONDO RESERVA | J46: APORTE PATRONAL | K46: TOTAL PROVISIONES
A47: 1 | B47: Alan Brito Delgado | C47: Obreros | D47: 45200 | E47: =M5-L5 -> 548.275 | F47: =E47/12 -> 45.689583 | G47: =482/12 -> 40.166667 | H47: =E47/24 -> 22.844792 | I47: 0 | J47: =E47*12.15% -> 66.615413 | K47: =SUM(F47:J47) -> 175.31645
A48: 2 | B48: Nori Navas Robles | C48: Obreros | D48: 45201 | E48: =M6-L6 -> 548.275 | F48: =E48/12 -> 45.689583 | G48: =482/12 -> 40.166667 | H48: =E48/24 -> 22.844792 | I48: 0 | J48: =E48*12.15% -> 66.615413 | K48: =SUM(F48:J48) -> 175.31645
A49: 3 | B49: Zoila Vaca Martinez | C49: Obreros | D49: 45202 | E49: =M7-L7 -> 548.275 | F49: =E49/12 -> 45.689583 | G49: =482/12 -> 40.166667 | H49: =E49/24 -> 22.844792 | I49: 0 | J49: =E49*12.15% -> 66.615413 | K49: =SUM(F49:J49) -> 175.31645
A50: 4 | B50: Giuliana Armas | C50: Obreros | D50: 45203 | E50: =M8-L8 -> 548.275 | F50: =E50/12 -> 45.689583 | G50: =482/12 -> 40.166667 | H50: =E50/24 -> 22.844792 | I50: 0 | J50: =E50*12.15% -> 66.615413 | K50: =SUM(F50:J50) -> 175.31645
A51: 5 | B51: Valeria Cortez | C51: Obreros | D51: 45204 | E51: =M9-L9 -> 548.275 | F51: =E51/12 -> 45.689583 | G51: =482/12 -> 40.166667 | H51: =E51/24 -> 22.844792 | I51: 0 | J51: =E51*12.15% -> 66.615413 | K51: =SUM(F51:J51) -> 175.31645
A52: 6 | B52: Alan Brito Delgado | C52: Obreros | D52: 45205 | E52: =M10-L10 -> 548.275 | F52: =E52/12 -> 45.689583 | G52: =482/12 -> 40.166667 | H52: =E52/24 -> 22.844792 | I52: 0 | J52: =E52*12.15% -> 66.615413 | K52: =SUM(F52:J52) -> 175.31645
A53: 7 | B53: Nori Navas Robles | C53: Obreros | D53: 45206 | E53: =M11-L11 -> 548.275 | F53: =E53/12 -> 45.689583 | G53: =482/12 -> 40.166667 | H53: =E53/24 -> 22.844792 | I53: 0 | J53: =E53*12.15% -> 66.615413 | K53: =SUM(F53:J53) -> 175.31645
A54: 8 | B54: Zoila Vaca Martinez | C54: Obreros | D54: 45207 | E54: =M12-L12 -> 548.275 | F54: =E54/12 -> 45.689583 | G54: =482/12 -> 40.166667 | H54: =E54/24 -> 22.844792 | I54: 0 | J54: =E54*12.15% -> 66.615413 | K54: =SUM(F54:J54) -> 175.31645
A55: 9 | B55: Giuliana Armas | C55: Obreros | D55: 45208 | E55: =M13-L13 -> 548.275 | F55: =E55/12 -> 45.689583 | G55: =482/12 -> 40.166667 | H55: =E55/24 -> 22.844792 | I55: 0 | J55: =E55*12.15% -> 66.615413 | K55: =SUM(F55:J55) -> 175.31645
A56: 10 | B56: Valeria Cortez | C56: Obreros | D56: 45209 | E56: =M14-L14 -> 548.275 | F56: =E56/12 -> 45.689583 | G56: =482/12 -> 40.166667 | H56: =E56/24 -> 22.844792 | I56: 0 | J56: =E56*12.15% -> 66.615413 | K56: =SUM(F56:J56) -> 175.31645
A57: 11 | B57: Alan Brito Delgado | C57: Obreros | D57: 45210 | E57: =M15-L15 -> 548.275 | F57: =E57/12 -> 45.689583 | G57: =482/12 -> 40.166667 | H57: =E57/24 -> 22.844792 | I57: 0 | J57: =E57*12.15% -> 66.615413 | K57: =SUM(F57:J57) -> 175.31645
A58: 12 | B58: Nori Navas Robles | C58: Obreros | D58: 45211 | E58: =M16-L16 -> 548.275 | F58: =E58/12 -> 45.689583 | G58: =482/12 -> 40.166667 | H58: =E58/24 -> 22.844792 | I58: 0 | J58: =E58*12.15% -> 66.615413 | K58: =SUM(F58:J58) -> 175.31645
... A76: 30 | B76: Valeria Cortez | C76: Obreros | D76: 45229 | E76: =M34-L34 -> 548.275 | F76: =E76/12 -> 45.689583 | G76: =482/12 -> 40.166667 | H76: =E76/24 -> 22.844792 | I76: 0 | J76: =E76*12.15% -> 66.615413 | K76: =SUM(F76:J76) -> 175.31645
F77: =SUM(F47:F76) -> 1370.6875 | G77: =SUM(G47:G76) -> 1205 | H77: =SUM(H47:H76) -> 685.34375 | I77: =SUM(I47:I76) -> 0 | J77: =SUM(J47:J76) -> 1998.4624 | K77: =SUM(K47:K76) -> 5259.4936
B79: Mano de Obra Indirecta
A80: No. | B80: NOMBRES Y APELLIDOS | C80: CARGO | D80: FECHA INGRESO | E80: TOTAL DE INGRESOS | F80: XIII SUELDO | G80: XIV SUELDO | H80: VACACIONES | I80: FONDO RESERVA | J80: APORTE PATRONAL | K80: TOTAL PROVISIONES
A81: 1 | B81: Alan Brito Delgado | C81: Jefe de Producción | D81: 45200 | E81: =M39-L39 -> 896.25 | F81: =E81/12 -> 74.6875 | G81: =482/12 -> 40.166667 | H81: =E81/24 -> 37.34375 | I81: 0 | J81: =E81*12.15% -> 108.89437 | K81: =SUM(F81:J81) -> 261.09229
A82: 2 | B82: Nori Navas Robles | C82: Supervisor | D82: 45201 | E82: =M40-L40 -> 799.375 | F82: =E82/12 -> 66.614583 | G82: =482/12 -> 40.166667 | H82: =E82/24 -> 33.307292 | I82: 0 | J82: =E82*12.15% -> 97.124062 | K82: =SUM(F82:J82) -> 237.2126
F83: =SUM(F81:F82) -> 141.30208 | G83: =SUM(G81:G82) -> 80.333333 | H83: =SUM(H81:H82) -> 70.651042 | I83: =SUM(I81:I82) -> 0 | J83: =SUM(J81:J82) -> 206.01844 | K83: =SUM(K81:K82) -> 498.3049

Sheet Hoja2
